[
{"ph":"C","name":"CPU Count","ts":700,"pid":1,"args":{"CPUS":14}},
{"ph":"C","name":"CPU Load 0.0-1.0","ts":700,"pid":1,"args":{"load":0}},
{"ph":"B","name":"mill /Users/tunguyen/Desktop/DELETEME/mill-scheduler-repro/tools/mill-1.1.6 compileLab","cat":"job","ts":1431,"pid":1,"tid":1},
{"ph":"B","name":"meta-level 0","cat":"job","ts":62548,"pid":1,"tid":1},
{"ph":"B","name":"meta-level 1","cat":"job","ts":63104,"pid":1,"tid":1},
{"ph":"B","name":"resolve millBuildRootModuleResult","cat":"job","ts":176068,"pid":1,"tid":1},
{"ph":"E","ts":234093,"pid":1,"tid":1},
{"ph":"B","name":"planning","cat":"job","ts":235772,"pid":1,"tid":1},
{"ph":"E","ts":284546,"pid":1,"tid":1},
{"ph":"B","name":"execution","cat":"job","ts":285173,"pid":1,"tid":1},
{"ph":"B","name":"scriptSources","cat":"job","ts":296123,"pid":1,"tid":2},
{"ph":"B","name":"javacOptions","cat":"job","ts":296280,"pid":1,"tid":3},
{"ph":"B","name":"millVersion","cat":"job","ts":296371,"pid":1,"tid":4},
{"ph":"B","name":"sources.super.javalib.JavaModule","cat":"job","ts":296445,"pid":1,"tid":5},
{"ph":"E","ts":317509,"pid":1,"tid":5},
{"ph":"E","ts":317545,"pid":1,"tid":4},
{"ph":"E","ts":317600,"pid":1,"tid":2},
{"ph":"B","name":"mandatoryJavacOptions","cat":"job","ts":317630,"pid":1,"tid":5},
{"ph":"E","ts":317758,"pid":1,"tid":3},
{"ph":"B","name":"mill.javalib.JvmWorkerModule/repositories","cat":"job","ts":317769,"pid":1,"tid":2},
{"ph":"B","name":"mill.javalib.JvmWorkerModule/checkGradleModules","cat":"job","ts":317838,"pid":1,"tid":3},
{"ph":"B","name":"mill.javalib.CoursierConfigModule/coursierEnv","cat":"job","ts":317931,"pid":1,"tid":4},
{"ph":"E","ts":318828,"pid":1,"tid":5},
{"ph":"E","ts":318912,"pid":1,"tid":2},
{"ph":"B","name":"mill.javalib.JvmWorkerModule/zincLogDebug","cat":"job","ts":318923,"pid":1,"tid":5},
{"ph":"B","name":"mill.javalib.JvmWorkerModule/useFileLocks","cat":"job","ts":319016,"pid":1,"tid":2},
{"ph":"E","ts":319187,"pid":1,"tid":3},
{"ph":"B","name":"upstreamCompileOutput","cat":"job","ts":319281,"pid":1,"tid":3},
{"ph":"E","ts":320116,"pid":1,"tid":2},
{"ph":"E","ts":320166,"pid":1,"tid":5},
{"ph":"E","ts":320274,"pid":1,"tid":4},
{"ph":"B","name":"platformSuffix","cat":"job","ts":320282,"pid":1,"tid":5},
{"ph":"B","name":"resolvedDepsWarnNonPlatform","cat":"job","ts":320390,"pid":1,"tid":2},
{"ph":"B","name":"mvnDeps","cat":"job","ts":320513,"pid":1,"tid":4},
{"ph":"E","ts":320637,"pid":1,"tid":3},
{"ph":"B","name":"mandatoryMvnDeps.super.meta.BootstrapRootModule","cat":"job","ts":320739,"pid":1,"tid":3},
{"ph":"E","ts":321324,"pid":1,"tid":5},
{"ph":"E","ts":321407,"pid":1,"tid":2},
{"ph":"B","name":"scalaVersion","cat":"job","ts":321424,"pid":1,"tid":5},
{"ph":"E","ts":321570,"pid":1,"tid":4},
{"ph":"B","name":"compileMvnDeps","cat":"job","ts":321583,"pid":1,"tid":2},
{"ph":"B","name":"cliImports","cat":"job","ts":321668,"pid":1,"tid":4},
{"ph":"E","ts":322404,"pid":1,"tid":5},
{"ph":"B","name":"bomMvnDeps","cat":"job","ts":322501,"pid":1,"tid":5},
{"ph":"E","ts":322657,"pid":1,"tid":4},
{"ph":"B","name":"depManagement","cat":"job","ts":322771,"pid":1,"tid":4},
{"ph":"E","ts":323394,"pid":1,"tid":5},
{"ph":"B","name":"transitiveCoursierProjects","cat":"job","ts":323507,"pid":1,"tid":5},
{"ph":"E","ts":323623,"pid":1,"tid":4},
{"ph":"B","name":"repositories","cat":"job","ts":323704,"pid":1,"tid":4},
{"ph":"E","ts":324499,"pid":1,"tid":4},
{"ph":"B","name":"checkGradleModules","cat":"job","ts":324592,"pid":1,"tid":4},
{"ph":"E","ts":324705,"pid":1,"tid":5},
{"ph":"B","name":"artifactTypes","cat":"job","ts":324791,"pid":1,"tid":5},
{"ph":"E","ts":325463,"pid":1,"tid":4},
{"ph":"B","name":"unmanagedClasspath","cat":"job","ts":325541,"pid":1,"tid":4},
{"ph":"E","ts":326305,"pid":1,"tid":4},
{"ph":"B","name":"unmanagedClasspathExistenceCheck","cat":"job","ts":326394,"pid":1,"tid":4},
{"ph":"E","ts":327074,"pid":1,"tid":4},
{"ph":"B","name":"compileResources","cat":"job","ts":327146,"pid":1,"tid":4},
{"ph":"E","ts":327956,"pid":1,"tid":5},
{"ph":"B","name":"mandatoryScalacOptions","cat":"job","ts":328030,"pid":1,"tid":5},
{"ph":"E","ts":328136,"pid":1,"tid":4},
{"ph":"B","name":"scalacPluginMvnDeps","cat":"job","ts":328206,"pid":1,"tid":4},
{"ph":"E","ts":328830,"pid":1,"tid":5},
{"ph":"B","name":"scalacOptions.super.scalalib.ScalaModule","cat":"job","ts":328914,"pid":1,"tid":5},
{"ph":"E","ts":329746,"pid":1,"tid":5},
{"ph":"B","name":"zincAuxiliaryClassFileExtensions.super.javalib.JavaModule","cat":"job","ts":329809,"pid":1,"tid":5},
{"ph":"E","ts":330750,"pid":1,"tid":5},
{"ph":"B","name":"jvmId","cat":"job","ts":330853,"pid":1,"tid":5},
{"ph":"E","ts":331587,"pid":1,"tid":5},
{"ph":"B","name":"jvmIndexVersion","cat":"job","ts":331666,"pid":1,"tid":5},
{"ph":"E","ts":332628,"pid":1,"tid":5},
{"ph":"B","name":"zincReportCachedProblems","cat":"job","ts":332724,"pid":1,"tid":5},
{"ph":"E","ts":333555,"pid":1,"tid":5},
{"ph":"B","name":"runClasspath.super.RunModule","cat":"job","ts":333646,"pid":1,"tid":5},
{"ph":"E","ts":334532,"pid":1,"tid":5},
{"ph":"B","name":"transitiveLocalClasspath","cat":"job","ts":334619,"pid":1,"tid":5},
{"ph":"E","ts":335453,"pid":1,"tid":5},
{"ph":"B","name":"localRunClasspath.super.RunModule","cat":"job","ts":335533,"pid":1,"tid":5},
{"ph":"E","ts":336155,"pid":1,"tid":2},
{"ph":"B","name":"resources.super.javalib.JavaModule","cat":"job","ts":336253,"pid":1,"tid":2},
{"ph":"E","ts":336426,"pid":1,"tid":4},
{"ph":"E","ts":336447,"pid":1,"tid":5},
{"ph":"E","ts":336516,"pid":1,"tid":3},
{"ph":"B","name":"parseBuildFiles","cat":"job","ts":337205,"pid":1,"tid":3},
{"ph":"B","name":"runMvnDeps","cat":"job","ts":337277,"pid":1,"tid":5},
{"ph":"B","name":"scalaLibraryMvnDeps","cat":"job","ts":337329,"pid":1,"tid":4},
{"ph":"E","ts":337705,"pid":1,"tid":2},
{"ph":"B","name":"scalacOptions","cat":"job","ts":337949,"pid":1,"tid":2},
{"ph":"E","ts":338830,"pid":1,"tid":2},
{"ph":"B","name":"jvmVersion","cat":"job","ts":338922,"pid":1,"tid":2},
{"ph":"E","ts":339468,"pid":1,"tid":5},
{"ph":"B","name":"mandatoryMvnDeps","cat":"job","ts":339566,"pid":1,"tid":5},
{"ph":"E","ts":339749,"pid":1,"tid":2},
{"ph":"B","name":"sources","cat":"job","ts":339836,"pid":1,"tid":2},
{"ph":"E","ts":340952,"pid":1,"tid":2},
{"ph":"E","ts":341000,"pid":1,"tid":4},
{"ph":"E","ts":341069,"pid":1,"tid":5},
{"ph":"B","name":"zincAuxiliaryClassFileExtensions","cat":"job","ts":341099,"pid":1,"tid":4},
{"ph":"B","name":"mill.javalib.JvmWorkerModule/classpath","cat":"job","ts":341263,"pid":1,"tid":5},
{"ph":"B","name":"localCompileClasspath","cat":"job","ts":341345,"pid":1,"tid":2},
{"ph":"E","ts":342293,"pid":1,"tid":4},
{"ph":"B","name":"javaHome","cat":"job","ts":342550,"pid":1,"tid":4},
{"ph":"E","ts":343548,"pid":1,"tid":2},
{"ph":"B","name":"scalaCompilerBridge","cat":"job","ts":343629,"pid":1,"tid":2},
{"ph":"E","ts":363011,"pid":1,"tid":4},
{"ph":"B","name":"scalaCompilerClasspath","cat":"job","ts":363220,"pid":1,"tid":4},
{"ph":"E","ts":503846,"pid":1,"tid":4},
{"ph":"B","name":"enablePluginScalacOptions","cat":"job","ts":503942,"pid":1,"tid":4},
{"ph":"E","ts":513660,"pid":1,"tid":4},
{"ph":"B","name":"scalacPluginClasspath","cat":"job","ts":513752,"pid":1,"tid":4},
{"ph":"E","ts":514139,"pid":1,"tid":3},
{"ph":"B","name":"generatedScriptSources","cat":"job","ts":514333,"pid":1,"tid":3},
{"ph":"E","ts":529987,"pid":1,"tid":2},
{"ph":"B","name":"allScalacOptions","cat":"job","ts":530161,"pid":1,"tid":2},
{"ph":"E","ts":531255,"pid":1,"tid":2},
{"ph":"B","name":"resolvedMvnDeps.super.javalib.JavaModule","cat":"job","ts":531461,"pid":1,"tid":2},
{"ph":"E","ts":543762,"pid":1,"tid":3},
{"ph":"B","name":"resolvedRunMvnDeps","cat":"job","ts":543873,"pid":1,"tid":3},
{"ph":"E","ts":544117,"pid":1,"tid":4},
{"ph":"B","name":"wrappedSources","cat":"job","ts":545014,"pid":1,"tid":4},
{"ph":"E","ts":545809,"pid":1,"tid":4},
{"ph":"B","name":"generatedSources","cat":"job","ts":545879,"pid":1,"tid":4},
{"ph":"E","ts":546580,"pid":1,"tid":4},
{"ph":"B","name":"resources","cat":"job","ts":546651,"pid":1,"tid":4},
{"ph":"E","ts":547382,"pid":1,"tid":4},
{"ph":"B","name":"allSources","cat":"job","ts":547491,"pid":1,"tid":4},
{"ph":"E","ts":548207,"pid":1,"tid":4},
{"ph":"B","name":"allSourceFiles","cat":"job","ts":548308,"pid":1,"tid":4},
{"ph":"E","ts":551524,"pid":1,"tid":4},
{"ph":"B","name":"zincIncrementalCompilation","cat":"job","ts":551644,"pid":1,"tid":4},
{"ph":"E","ts":552547,"pid":1,"tid":4},
{"ph":"E","ts":634897,"pid":1,"tid":2},
{"ph":"B","name":"resolvedMvnDeps","cat":"job","ts":635006,"pid":1,"tid":2},
{"ph":"E","ts":636898,"pid":1,"tid":2},
{"ph":"B","name":"compileClasspath","cat":"job","ts":636986,"pid":1,"tid":2},
{"ph":"E","ts":638705,"pid":1,"tid":2},
{"ph":"E","ts":749046,"pid":1,"tid":3},
{"ph":"E","ts":752608,"pid":1,"tid":5},
{"ph":"B","name":"mill.javalib.JvmWorkerModule/internalWorkerClassLoader","cat":"job","ts":752806,"pid":1,"tid":5},
{"ph":"E","ts":757525,"pid":1,"tid":5},
{"ph":"B","name":"mill.javalib.JvmWorkerModule/internalWorker","cat":"job","ts":757679,"pid":1,"tid":5},
{"ph":"E","ts":773082,"pid":1,"tid":5},
{"ph":"B","name":"compile","cat":"job","ts":773277,"pid":1,"tid":5},
{"ph":"C","name":"CPU Count","ts":1006002,"pid":1,"args":{"CPUS":14}},
{"ph":"C","name":"CPU Load 0.0-1.0","ts":1006002,"pid":1,"args":{"load":0.4806590257879656}},
{"ph":"C","name":"CPU Count","ts":2011107,"pid":1,"args":{"CPUS":14}},
{"ph":"C","name":"CPU Load 0.0-1.0","ts":2011107,"pid":1,"args":{"load":0.2794853466761973}},
{"ph":"C","name":"CPU Count","ts":3011889,"pid":1,"args":{"CPUS":14}},
{"ph":"C","name":"CPU Load 0.0-1.0","ts":3011889,"pid":1,"args":{"load":0.4192390524048816}},
{"ph":"C","name":"CPU Count","ts":4016937,"pid":1,"args":{"CPUS":14}},
{"ph":"C","name":"CPU Load 0.0-1.0","ts":4016937,"pid":1,"args":{"load":0.4483250178189594}},
{"ph":"E","ts":4684876,"pid":1,"tid":5},
{"ph":"B","name":"localRunClasspath","cat":"job","ts":4685040,"pid":1,"tid":5},
{"ph":"B","name":"codeSignatures","cat":"job","ts":4685100,"pid":1,"tid":4},
{"ph":"E","ts":4686141,"pid":1,"tid":5},
{"ph":"B","name":"localClasspath","cat":"job","ts":4686216,"pid":1,"tid":5},
{"ph":"E","ts":4687015,"pid":1,"tid":5},
{"ph":"B","name":"runClasspath","cat":"job","ts":4687099,"pid":1,"tid":5},
{"ph":"E","ts":4688647,"pid":1,"tid":5},
{"ph":"B","name":"Analyzing classes (batch 2/4)","cat":"job","ts":4691180,"pid":1,"tid":5},
{"ph":"B","name":"Analyzing classes (batch 3/4)","cat":"job","ts":4691259,"pid":1,"tid":3},
{"ph":"B","name":"Analyzing classes (batch 1/4)","cat":"job","ts":4691334,"pid":1,"tid":2},
{"ph":"B","name":"Analyzing classes (batch 4/4)","cat":"job","ts":4691534,"pid":1,"tid":6},
{"ph":"E","ts":4777291,"pid":1,"tid":5},
{"ph":"E","ts":4787244,"pid":1,"tid":6},
{"ph":"E","ts":4788267,"pid":1,"tid":3},
{"ph":"E","ts":4788322,"pid":1,"tid":2},
{"ph":"E","ts":4948391,"pid":1,"tid":4},
{"ph":"B","name":"millBuildRootModuleResult","cat":"job","ts":4948545,"pid":1,"tid":4},
{"ph":"E","ts":4953034,"pid":1,"tid":4},
{"ph":"E","ts":4963467,"pid":1,"tid":1},
{"ph":"E","ts":4973233,"pid":1,"tid":1},
{"ph":"C","name":"CPU Count","ts":5022019,"pid":1,"args":{"CPUS":14}},
{"ph":"C","name":"CPU Load 0.0-1.0","ts":5022019,"pid":1,"args":{"load":0.48283261802575106}},
{"ph":"B","name":"resolve compileLab","cat":"job","ts":5076758,"pid":1,"tid":1},
{"ph":"E","ts":5149315,"pid":1,"tid":1},
{"ph":"B","name":"planning","cat":"job","ts":5150093,"pid":1,"tid":1},
{"ph":"E","ts":5197379,"pid":1,"tid":1},
{"ph":"B","name":"execution","cat":"job","ts":5197602,"pid":1,"tid":1},
{"ph":"B","name":"common.javacOptions","cat":"job","ts":5208250,"pid":1,"tid":6},
{"ph":"B","name":"common.scalaVersion","cat":"job","ts":5208329,"pid":1,"tid":2},
{"ph":"B","name":"mill.javalib.CoursierConfigModule/coursierEnv","cat":"job","ts":5208375,"pid":1,"tid":4},
{"ph":"B","name":"common.mandatoryJavacOptions","cat":"job","ts":5208441,"pid":1,"tid":5},
{"ph":"E","ts":5236579,"pid":1,"tid":6},
{"ph":"E","ts":5236620,"pid":1,"tid":4},
{"ph":"E","ts":5236646,"pid":1,"tid":5},
{"ph":"E","ts":5236675,"pid":1,"tid":2},
{"ph":"B","name":"mill.javalib.JvmWorkerModule/repositories","cat":"job","ts":5236685,"pid":1,"tid":6},
{"ph":"B","name":"mill.javalib.JvmWorkerModule/checkGradleModules","cat":"job","ts":5236742,"pid":1,"tid":5},
{"ph":"B","name":"mill.javalib.JvmWorkerModule/zincLogDebug","cat":"job","ts":5236791,"pid":1,"tid":2},
{"ph":"B","name":"mill.javalib.JvmWorkerModule/useFileLocks","cat":"job","ts":5236852,"pid":1,"tid":4},
{"ph":"E","ts":5237418,"pid":1,"tid":4},
{"ph":"E","ts":5237474,"pid":1,"tid":6},
{"ph":"B","name":"common.upstreamCompileOutput","cat":"job","ts":5237487,"pid":1,"tid":4},
{"ph":"B","name":"common.sources","cat":"job","ts":5237521,"pid":1,"tid":6},
{"ph":"E","ts":5237588,"pid":1,"tid":5},
{"ph":"E","ts":5237640,"pid":1,"tid":2},
{"ph":"B","name":"common.generatedSources","cat":"job","ts":5237653,"pid":1,"tid":5},
{"ph":"B","name":"common.wrappedSources","cat":"job","ts":5237692,"pid":1,"tid":2},
{"ph":"E","ts":5238175,"pid":1,"tid":5},
{"ph":"B","name":"common.resolvedDepsWarnNonPlatform","cat":"job","ts":5238211,"pid":1,"tid":5},
{"ph":"E","ts":5238269,"pid":1,"tid":2},
{"ph":"B","name":"common.platformSuffix","cat":"job","ts":5238305,"pid":1,"tid":2},
{"ph":"E","ts":5238435,"pid":1,"tid":4},
{"ph":"B","name":"common.mvnDeps","cat":"job","ts":5238488,"pid":1,"tid":4},
{"ph":"E","ts":5238703,"pid":1,"tid":5},
{"ph":"B","name":"common.mandatoryMvnDeps.super.javalib.JavaModule","cat":"job","ts":5238739,"pid":1,"tid":5},
{"ph":"E","ts":5238795,"pid":1,"tid":2},
{"ph":"B","name":"common.compileMvnDeps","cat":"job","ts":5238839,"pid":1,"tid":2},
{"ph":"E","ts":5238966,"pid":1,"tid":4},
{"ph":"B","name":"common.runMvnDeps","cat":"job","ts":5239015,"pid":1,"tid":4},
{"ph":"E","ts":5239406,"pid":1,"tid":2},
{"ph":"E","ts":5239459,"pid":1,"tid":5},
{"ph":"B","name":"common.bomMvnDeps","cat":"job","ts":5239473,"pid":1,"tid":2},
{"ph":"B","name":"common.depManagement","cat":"job","ts":5239517,"pid":1,"tid":5},
{"ph":"E","ts":5239583,"pid":1,"tid":4},
{"ph":"B","name":"common.transitiveCoursierProjects","cat":"job","ts":5239630,"pid":1,"tid":4},
{"ph":"E","ts":5239997,"pid":1,"tid":5},
{"ph":"E","ts":5240017,"pid":1,"tid":2},
{"ph":"B","name":"common.repositories","cat":"job","ts":5240035,"pid":1,"tid":5},
{"ph":"B","name":"common.checkGradleModules","cat":"job","ts":5240069,"pid":1,"tid":2},
{"ph":"E","ts":5240233,"pid":1,"tid":4},
{"ph":"B","name":"common.artifactTypes","cat":"job","ts":5240273,"pid":1,"tid":4},
{"ph":"E","ts":5240483,"pid":1,"tid":5},
{"ph":"B","name":"common.unmanagedClasspath","cat":"job","ts":5240541,"pid":1,"tid":5},
{"ph":"E","ts":5240668,"pid":1,"tid":2},
{"ph":"B","name":"common.unmanagedClasspathExistenceCheck","cat":"job","ts":5240704,"pid":1,"tid":2},
{"ph":"E","ts":5240963,"pid":1,"tid":5},
{"ph":"B","name":"common.compileResources","cat":"job","ts":5240991,"pid":1,"tid":5},
{"ph":"E","ts":5241119,"pid":1,"tid":2},
{"ph":"B","name":"common.mandatoryScalacOptions","cat":"job","ts":5241146,"pid":1,"tid":2},
{"ph":"E","ts":5241562,"pid":1,"tid":2},
{"ph":"B","name":"common.scalacPluginMvnDeps","cat":"job","ts":5241589,"pid":1,"tid":2},
{"ph":"E","ts":5241848,"pid":1,"tid":5},
{"ph":"B","name":"common.scalacOptions","cat":"job","ts":5241887,"pid":1,"tid":5},
{"ph":"E","ts":5242104,"pid":1,"tid":2},
{"ph":"B","name":"common.zincAuxiliaryClassFileExtensions.super.javalib.JavaModule","cat":"job","ts":5242134,"pid":1,"tid":2},
{"ph":"E","ts":5242352,"pid":1,"tid":5},
{"ph":"B","name":"common.jvmId","cat":"job","ts":5242393,"pid":1,"tid":5},
{"ph":"E","ts":5242817,"pid":1,"tid":2},
{"ph":"B","name":"common.jvmIndexVersion","cat":"job","ts":5242858,"pid":1,"tid":2},
{"ph":"E","ts":5242993,"pid":1,"tid":5},
{"ph":"B","name":"common.zincReportCachedProblems","cat":"job","ts":5243028,"pid":1,"tid":5},
{"ph":"E","ts":5243630,"pid":1,"tid":4},
{"ph":"B","name":"chain0.scalaVersion","cat":"job","ts":5243678,"pid":1,"tid":4},
{"ph":"E","ts":5243848,"pid":1,"tid":2},
{"ph":"B","name":"chain0.javacOptions","cat":"job","ts":5243878,"pid":1,"tid":2},
{"ph":"E","ts":5244506,"pid":1,"tid":5},
{"ph":"B","name":"chain0.mandatoryJavacOptions","cat":"job","ts":5244537,"pid":1,"tid":5},
{"ph":"E","ts":5244748,"pid":1,"tid":2},
{"ph":"E","ts":5244798,"pid":1,"tid":6},
{"ph":"E","ts":5244818,"pid":1,"tid":4},
{"ph":"B","name":"chain0.sources","cat":"job","ts":5244848,"pid":1,"tid":2},
{"ph":"B","name":"chain0.wrappedSources","cat":"job","ts":5244895,"pid":1,"tid":4},
{"ph":"B","name":"chain0.generatedSources","cat":"job","ts":5244927,"pid":1,"tid":6},
{"ph":"E","ts":5245022,"pid":1,"tid":5},
{"ph":"B","name":"chain0.resolvedDepsWarnNonPlatform","cat":"job","ts":5245057,"pid":1,"tid":5},
{"ph":"E","ts":5248882,"pid":1,"tid":6},
{"ph":"E","ts":5248904,"pid":1,"tid":4},
{"ph":"B","name":"chain0.platformSuffix","cat":"job","ts":5249018,"pid":1,"tid":6},
{"ph":"B","name":"chain0.mvnDeps","cat":"job","ts":5249058,"pid":1,"tid":4},
{"ph":"E","ts":5249120,"pid":1,"tid":5},
{"ph":"B","name":"chain0.mandatoryMvnDeps.super.javalib.JavaModule","cat":"job","ts":5249156,"pid":1,"tid":5},
{"ph":"E","ts":5249663,"pid":1,"tid":6},
{"ph":"E","ts":5249693,"pid":1,"tid":4},
{"ph":"B","name":"chain0.compileMvnDeps","cat":"job","ts":5249741,"pid":1,"tid":4},
{"ph":"B","name":"chain0.runMvnDeps","cat":"job","ts":5249787,"pid":1,"tid":6},
{"ph":"E","ts":5249832,"pid":1,"tid":2},
{"ph":"B","name":"chain0.bomMvnDeps","cat":"job","ts":5249854,"pid":1,"tid":2},
{"ph":"E","ts":5253884,"pid":1,"tid":5},
{"ph":"B","name":"chain0.depManagement","cat":"job","ts":5253916,"pid":1,"tid":5},
{"ph":"E","ts":5254091,"pid":1,"tid":6},
{"ph":"E","ts":5254115,"pid":1,"tid":2},
{"ph":"E","ts":5254137,"pid":1,"tid":4},
{"ph":"B","name":"chain0.repositories","cat":"job","ts":5254140,"pid":1,"tid":6},
{"ph":"B","name":"chain0.artifactTypes","cat":"job","ts":5254180,"pid":1,"tid":4},
{"ph":"B","name":"chain0.checkGradleModules","cat":"job","ts":5254217,"pid":1,"tid":2},
{"ph":"E","ts":5254377,"pid":1,"tid":5},
{"ph":"B","name":"chain0.unmanagedClasspath","cat":"job","ts":5254404,"pid":1,"tid":5},
{"ph":"E","ts":5254607,"pid":1,"tid":6},
{"ph":"B","name":"chain0.unmanagedClasspathExistenceCheck","cat":"job","ts":5254638,"pid":1,"tid":6},
{"ph":"E","ts":5254761,"pid":1,"tid":2},
{"ph":"B","name":"chain0.compileResources","cat":"job","ts":5254792,"pid":1,"tid":2},
{"ph":"E","ts":5254846,"pid":1,"tid":4},
{"ph":"B","name":"chain0.mandatoryScalacOptions","cat":"job","ts":5254876,"pid":1,"tid":4},
{"ph":"E","ts":5254921,"pid":1,"tid":5},
{"ph":"B","name":"chain0.scalacPluginMvnDeps","cat":"job","ts":5254954,"pid":1,"tid":5},
{"ph":"E","ts":5255055,"pid":1,"tid":6},
{"ph":"B","name":"chain0.scalacOptions","cat":"job","ts":5255083,"pid":1,"tid":6},
{"ph":"E","ts":5255293,"pid":1,"tid":4},
{"ph":"B","name":"chain0.zincAuxiliaryClassFileExtensions.super.javalib.JavaModule","cat":"job","ts":5255323,"pid":1,"tid":4},
{"ph":"E","ts":5255381,"pid":1,"tid":2},
{"ph":"E","ts":5255412,"pid":1,"tid":5},
{"ph":"B","name":"chain0.jvmId","cat":"job","ts":5255423,"pid":1,"tid":2},
{"ph":"B","name":"chain0.jvmIndexVersion","cat":"job","ts":5255456,"pid":1,"tid":5},
{"ph":"E","ts":5255580,"pid":1,"tid":6},
{"ph":"B","name":"chain0.zincReportCachedProblems","cat":"job","ts":5255652,"pid":1,"tid":6},
{"ph":"E","ts":5255946,"pid":1,"tid":2},
{"ph":"E","ts":5255967,"pid":1,"tid":5},
{"ph":"B","name":"chain1.scalaVersion","cat":"job","ts":5255984,"pid":1,"tid":2},
{"ph":"B","name":"chain1.javacOptions","cat":"job","ts":5256014,"pid":1,"tid":5},
{"ph":"E","ts":5256069,"pid":1,"tid":4},
{"ph":"B","name":"chain1.mandatoryJavacOptions","cat":"job","ts":5256100,"pid":1,"tid":4},
{"ph":"E","ts":5256148,"pid":1,"tid":6},
{"ph":"B","name":"chain1.sources","cat":"job","ts":5256176,"pid":1,"tid":6},
{"ph":"E","ts":5256585,"pid":1,"tid":4},
{"ph":"E","ts":5256611,"pid":1,"tid":2},
{"ph":"E","ts":5256622,"pid":1,"tid":5},
{"ph":"B","name":"chain1.generatedSources","cat":"job","ts":5256636,"pid":1,"tid":4},
{"ph":"B","name":"chain1.resolvedDepsWarnNonPlatform","cat":"job","ts":5256661,"pid":1,"tid":5},
{"ph":"B","name":"chain1.wrappedSources","cat":"job","ts":5256695,"pid":1,"tid":2},
{"ph":"E","ts":5257121,"pid":1,"tid":2},
{"ph":"E","ts":5257136,"pid":1,"tid":5},
{"ph":"E","ts":5257155,"pid":1,"tid":4},
{"ph":"B","name":"chain1.mvnDeps","cat":"job","ts":5257162,"pid":1,"tid":5},
{"ph":"B","name":"chain1.platformSuffix","cat":"job","ts":5257192,"pid":1,"tid":2},
{"ph":"B","name":"chain1.mandatoryMvnDeps.super.javalib.JavaModule","cat":"job","ts":5257224,"pid":1,"tid":4},
{"ph":"E","ts":5257646,"pid":1,"tid":5},
{"ph":"B","name":"chain1.compileMvnDeps","cat":"job","ts":5257679,"pid":1,"tid":5},
{"ph":"E","ts":5257729,"pid":1,"tid":2},
{"ph":"B","name":"chain1.runMvnDeps","cat":"job","ts":5257757,"pid":1,"tid":2},
{"ph":"E","ts":5257846,"pid":1,"tid":4},
{"ph":"B","name":"chain1.bomMvnDeps","cat":"job","ts":5257879,"pid":1,"tid":4},
{"ph":"E","ts":5258125,"pid":1,"tid":5},
{"ph":"E","ts":5258151,"pid":1,"tid":2},
{"ph":"B","name":"chain1.depManagement","cat":"job","ts":5258162,"pid":1,"tid":5},
{"ph":"B","name":"chain1.repositories","cat":"job","ts":5258198,"pid":1,"tid":2},
{"ph":"E","ts":5258267,"pid":1,"tid":4},
{"ph":"B","name":"chain1.checkGradleModules","cat":"job","ts":5258296,"pid":1,"tid":4},
{"ph":"E","ts":5258716,"pid":1,"tid":5},
{"ph":"B","name":"chain1.artifactTypes","cat":"job","ts":5258749,"pid":1,"tid":5},
{"ph":"E","ts":5258794,"pid":1,"tid":2},
{"ph":"E","ts":5258817,"pid":1,"tid":4},
{"ph":"B","name":"chain1.unmanagedClasspath","cat":"job","ts":5258831,"pid":1,"tid":2},
{"ph":"B","name":"chain1.unmanagedClasspathExistenceCheck","cat":"job","ts":5258929,"pid":1,"tid":4},
{"ph":"E","ts":5259227,"pid":1,"tid":2},
{"ph":"B","name":"chain1.compileResources","cat":"job","ts":5259259,"pid":1,"tid":2},
{"ph":"E","ts":5259485,"pid":1,"tid":4},
{"ph":"E","ts":5259518,"pid":1,"tid":5},
{"ph":"B","name":"chain1.scalacPluginMvnDeps","cat":"job","ts":5259557,"pid":1,"tid":5},
{"ph":"B","name":"chain1.mandatoryScalacOptions","cat":"job","ts":5259708,"pid":1,"tid":4},
{"ph":"E","ts":5259758,"pid":1,"tid":2},
{"ph":"B","name":"chain1.scalacOptions","cat":"job","ts":5259789,"pid":1,"tid":2},
{"ph":"E","ts":5260168,"pid":1,"tid":5},
{"ph":"E","ts":5260181,"pid":1,"tid":4},
{"ph":"E","ts":5260204,"pid":1,"tid":2},
{"ph":"B","name":"chain1.jvmId","cat":"job","ts":5260208,"pid":1,"tid":4},
{"ph":"B","name":"chain1.jvmIndexVersion","cat":"job","ts":5260235,"pid":1,"tid":2},
{"ph":"B","name":"chain1.zincAuxiliaryClassFileExtensions.super.javalib.JavaModule","cat":"job","ts":5260272,"pid":1,"tid":5},
{"ph":"E","ts":5260720,"pid":1,"tid":2},
{"ph":"E","ts":5260739,"pid":1,"tid":4},
{"ph":"B","name":"chain1.zincReportCachedProblems","cat":"job","ts":5260745,"pid":1,"tid":2},
{"ph":"B","name":"chain2.scalaVersion","cat":"job","ts":5260776,"pid":1,"tid":4},
{"ph":"E","ts":5260930,"pid":1,"tid":6},
{"ph":"B","name":"chain2.javacOptions","cat":"job","ts":5260972,"pid":1,"tid":6},
{"ph":"E","ts":5261020,"pid":1,"tid":5},
{"ph":"B","name":"chain2.mandatoryJavacOptions","cat":"job","ts":5261051,"pid":1,"tid":5},
{"ph":"E","ts":5261205,"pid":1,"tid":4},
{"ph":"E","ts":5261225,"pid":1,"tid":2},
{"ph":"B","name":"chain2.sources","cat":"job","ts":5261234,"pid":1,"tid":4},
{"ph":"B","name":"chain2.generatedSources","cat":"job","ts":5261266,"pid":1,"tid":2},
{"ph":"E","ts":5261383,"pid":1,"tid":6},
{"ph":"E","ts":5261408,"pid":1,"tid":5},
{"ph":"B","name":"chain2.wrappedSources","cat":"job","ts":5261413,"pid":1,"tid":6},
{"ph":"B","name":"chain2.resolvedDepsWarnNonPlatform","cat":"job","ts":5261450,"pid":1,"tid":5},
{"ph":"E","ts":5261709,"pid":1,"tid":2},
{"ph":"B","name":"chain2.platformSuffix","cat":"job","ts":5261745,"pid":1,"tid":2},
{"ph":"E","ts":5261806,"pid":1,"tid":6},
{"ph":"E","ts":5261833,"pid":1,"tid":5},
{"ph":"B","name":"chain2.mvnDeps","cat":"job","ts":5261844,"pid":1,"tid":6},
{"ph":"B","name":"chain2.mandatoryMvnDeps.super.javalib.JavaModule","cat":"job","ts":5261877,"pid":1,"tid":5},
{"ph":"E","ts":5262154,"pid":1,"tid":2},
{"ph":"B","name":"chain2.compileMvnDeps","cat":"job","ts":5262183,"pid":1,"tid":2},
{"ph":"E","ts":5262295,"pid":1,"tid":6},
{"ph":"B","name":"chain2.runMvnDeps","cat":"job","ts":5262326,"pid":1,"tid":6},
{"ph":"E","ts":5262373,"pid":1,"tid":5},
{"ph":"B","name":"chain2.bomMvnDeps","cat":"job","ts":5262400,"pid":1,"tid":5},
{"ph":"E","ts":5262597,"pid":1,"tid":2},
{"ph":"B","name":"chain2.depManagement","cat":"job","ts":5262626,"pid":1,"tid":2},
{"ph":"E","ts":5262710,"pid":1,"tid":6},
{"ph":"B","name":"chain2.repositories","cat":"job","ts":5262742,"pid":1,"tid":6},
{"ph":"E","ts":5262801,"pid":1,"tid":5},
{"ph":"B","name":"chain2.checkGradleModules","cat":"job","ts":5262830,"pid":1,"tid":5},
{"ph":"E","ts":5263027,"pid":1,"tid":2},
{"ph":"B","name":"chain2.artifactTypes","cat":"job","ts":5263057,"pid":1,"tid":2},
{"ph":"E","ts":5263217,"pid":1,"tid":6},
{"ph":"E","ts":5263248,"pid":1,"tid":5},
{"ph":"B","name":"chain2.unmanagedClasspath","cat":"job","ts":5263257,"pid":1,"tid":6},
{"ph":"B","name":"chain2.unmanagedClasspathExistenceCheck","cat":"job","ts":5263289,"pid":1,"tid":5},
{"ph":"E","ts":5263503,"pid":1,"tid":2},
{"ph":"B","name":"chain2.compileResources","cat":"job","ts":5263529,"pid":1,"tid":2},
{"ph":"E","ts":5263759,"pid":1,"tid":5},
{"ph":"E","ts":5263784,"pid":1,"tid":6},
{"ph":"B","name":"chain2.mandatoryScalacOptions","cat":"job","ts":5263795,"pid":1,"tid":5},
{"ph":"B","name":"chain2.scalacPluginMvnDeps","cat":"job","ts":5263830,"pid":1,"tid":6},
{"ph":"E","ts":5263968,"pid":1,"tid":2},
{"ph":"B","name":"chain2.scalacOptions","cat":"job","ts":5263993,"pid":1,"tid":2},
{"ph":"E","ts":5264313,"pid":1,"tid":6},
{"ph":"E","ts":5264331,"pid":1,"tid":5},
{"ph":"B","name":"chain2.zincAuxiliaryClassFileExtensions.super.javalib.JavaModule","cat":"job","ts":5264345,"pid":1,"tid":6},
{"ph":"B","name":"chain2.jvmId","cat":"job","ts":5264380,"pid":1,"tid":5},
{"ph":"E","ts":5264420,"pid":1,"tid":2},
{"ph":"B","name":"chain2.jvmIndexVersion","cat":"job","ts":5264450,"pid":1,"tid":2},
{"ph":"E","ts":5264936,"pid":1,"tid":5},
{"ph":"E","ts":5264967,"pid":1,"tid":2},
{"ph":"B","name":"chain2.zincReportCachedProblems","cat":"job","ts":5265015,"pid":1,"tid":5},
{"ph":"B","name":"chain3.scalaVersion","cat":"job","ts":5265043,"pid":1,"tid":2},
{"ph":"E","ts":5265086,"pid":1,"tid":6},
{"ph":"B","name":"chain3.javacOptions","cat":"job","ts":5265111,"pid":1,"tid":6},
{"ph":"E","ts":5265415,"pid":1,"tid":5},
{"ph":"B","name":"chain3.mandatoryJavacOptions","cat":"job","ts":5265448,"pid":1,"tid":5},
{"ph":"E","ts":5265485,"pid":1,"tid":6},
{"ph":"E","ts":5265497,"pid":1,"tid":2},
{"ph":"B","name":"chain3.sources","cat":"job","ts":5265514,"pid":1,"tid":6},
{"ph":"B","name":"chain3.generatedSources","cat":"job","ts":5265540,"pid":1,"tid":2},
{"ph":"E","ts":5265899,"pid":1,"tid":5},
{"ph":"B","name":"chain3.wrappedSources","cat":"job","ts":5265933,"pid":1,"tid":5},
{"ph":"E","ts":5265978,"pid":1,"tid":2},
{"ph":"B","name":"chain3.resolvedDepsWarnNonPlatform","cat":"job","ts":5266007,"pid":1,"tid":2},
{"ph":"E","ts":5266094,"pid":1,"tid":4},
{"ph":"B","name":"chain3.platformSuffix","cat":"job","ts":5266130,"pid":1,"tid":4},
{"ph":"E","ts":5266359,"pid":1,"tid":2},
{"ph":"E","ts":5266375,"pid":1,"tid":5},
{"ph":"B","name":"chain3.mvnDeps","cat":"job","ts":5266387,"pid":1,"tid":2},
{"ph":"B","name":"chain3.mandatoryMvnDeps.super.javalib.JavaModule","cat":"job","ts":5266417,"pid":1,"tid":5},
{"ph":"E","ts":5266588,"pid":1,"tid":4},
{"ph":"B","name":"chain3.compileMvnDeps","cat":"job","ts":5266623,"pid":1,"tid":4},
{"ph":"E","ts":5266781,"pid":1,"tid":2},
{"ph":"B","name":"chain3.runMvnDeps","cat":"job","ts":5266809,"pid":1,"tid":2},
{"ph":"E","ts":5266918,"pid":1,"tid":5},
{"ph":"B","name":"chain3.bomMvnDeps","cat":"job","ts":5266949,"pid":1,"tid":5},
{"ph":"E","ts":5267052,"pid":1,"tid":4},
{"ph":"B","name":"chain3.depManagement","cat":"job","ts":5267082,"pid":1,"tid":4},
{"ph":"E","ts":5267241,"pid":1,"tid":2},
{"ph":"B","name":"chain3.repositories","cat":"job","ts":5267273,"pid":1,"tid":2},
{"ph":"E","ts":5267392,"pid":1,"tid":5},
{"ph":"B","name":"chain3.checkGradleModules","cat":"job","ts":5267422,"pid":1,"tid":5},
{"ph":"E","ts":5267537,"pid":1,"tid":4},
{"ph":"B","name":"chain3.artifactTypes","cat":"job","ts":5267567,"pid":1,"tid":4},
{"ph":"E","ts":5267692,"pid":1,"tid":2},
{"ph":"B","name":"chain3.unmanagedClasspath","cat":"job","ts":5267721,"pid":1,"tid":2},
{"ph":"E","ts":5267908,"pid":1,"tid":5},
{"ph":"B","name":"chain3.unmanagedClasspathExistenceCheck","cat":"job","ts":5267938,"pid":1,"tid":5},
{"ph":"E","ts":5268010,"pid":1,"tid":4},
{"ph":"B","name":"chain3.compileResources","cat":"job","ts":5268036,"pid":1,"tid":4},
{"ph":"E","ts":5268203,"pid":1,"tid":2},
{"ph":"B","name":"chain3.mandatoryScalacOptions","cat":"job","ts":5268232,"pid":1,"tid":2},
{"ph":"E","ts":5268305,"pid":1,"tid":5},
{"ph":"B","name":"chain3.scalacPluginMvnDeps","cat":"job","ts":5268328,"pid":1,"tid":5},
{"ph":"E","ts":5268511,"pid":1,"tid":4},
{"ph":"B","name":"chain3.scalacOptions","cat":"job","ts":5268541,"pid":1,"tid":4},
{"ph":"E","ts":5268610,"pid":1,"tid":2},
{"ph":"B","name":"chain3.zincAuxiliaryClassFileExtensions.super.javalib.JavaModule","cat":"job","ts":5268637,"pid":1,"tid":2},
{"ph":"E","ts":5268677,"pid":1,"tid":5},
{"ph":"B","name":"chain3.jvmId","cat":"job","ts":5268702,"pid":1,"tid":5},
{"ph":"E","ts":5268938,"pid":1,"tid":4},
{"ph":"B","name":"chain3.jvmIndexVersion","cat":"job","ts":5268966,"pid":1,"tid":4},
{"ph":"E","ts":5269083,"pid":1,"tid":5},
{"ph":"B","name":"chain3.zincReportCachedProblems","cat":"job","ts":5269112,"pid":1,"tid":5},
{"ph":"E","ts":5269210,"pid":1,"tid":2},
{"ph":"B","name":"side0.scalaVersion","cat":"job","ts":5269234,"pid":1,"tid":2},
{"ph":"E","ts":5269335,"pid":1,"tid":4},
{"ph":"B","name":"side0.javacOptions","cat":"job","ts":5269364,"pid":1,"tid":4},
{"ph":"E","ts":5269504,"pid":1,"tid":5},
{"ph":"B","name":"side0.mandatoryJavacOptions","cat":"job","ts":5269529,"pid":1,"tid":5},
{"ph":"E","ts":5269637,"pid":1,"tid":2},
{"ph":"B","name":"side0.sources","cat":"job","ts":5269678,"pid":1,"tid":2},
{"ph":"E","ts":5269792,"pid":1,"tid":4},
{"ph":"B","name":"side0.generatedSources","cat":"job","ts":5269819,"pid":1,"tid":4},
{"ph":"E","ts":5269914,"pid":1,"tid":5},
{"ph":"B","name":"side0.wrappedSources","cat":"job","ts":5269944,"pid":1,"tid":5},
{"ph":"E","ts":5270275,"pid":1,"tid":4},
{"ph":"B","name":"side0.resolvedDepsWarnNonPlatform","cat":"job","ts":5270309,"pid":1,"tid":4},
{"ph":"E","ts":5270408,"pid":1,"tid":5},
{"ph":"B","name":"side0.platformSuffix","cat":"job","ts":5270437,"pid":1,"tid":5},
{"ph":"E","ts":5270644,"pid":1,"tid":6},
{"ph":"B","name":"side0.mvnDeps","cat":"job","ts":5270671,"pid":1,"tid":6},
{"ph":"E","ts":5270777,"pid":1,"tid":4},
{"ph":"B","name":"side0.mandatoryMvnDeps.super.javalib.JavaModule","cat":"job","ts":5270807,"pid":1,"tid":4},
{"ph":"E","ts":5270853,"pid":1,"tid":5},
{"ph":"B","name":"side0.compileMvnDeps","cat":"job","ts":5270883,"pid":1,"tid":5},
{"ph":"E","ts":5271127,"pid":1,"tid":6},
{"ph":"B","name":"side0.runMvnDeps","cat":"job","ts":5271160,"pid":1,"tid":6},
{"ph":"E","ts":5271406,"pid":1,"tid":5},
{"ph":"B","name":"side0.bomMvnDeps","cat":"job","ts":5271436,"pid":1,"tid":5},
{"ph":"E","ts":5271476,"pid":1,"tid":4},
{"ph":"B","name":"side0.depManagement","cat":"job","ts":5271498,"pid":1,"tid":4},
{"ph":"E","ts":5271657,"pid":1,"tid":6},
{"ph":"B","name":"side0.repositories","cat":"job","ts":5271689,"pid":1,"tid":6},
{"ph":"E","ts":5271859,"pid":1,"tid":5},
{"ph":"B","name":"side0.checkGradleModules","cat":"job","ts":5271886,"pid":1,"tid":5},
{"ph":"E","ts":5271979,"pid":1,"tid":4},
{"ph":"B","name":"side0.artifactTypes","cat":"job","ts":5272007,"pid":1,"tid":4},
{"ph":"E","ts":5272157,"pid":1,"tid":6},
{"ph":"B","name":"side0.unmanagedClasspath","cat":"job","ts":5272187,"pid":1,"tid":6},
{"ph":"E","ts":5272285,"pid":1,"tid":5},
{"ph":"B","name":"side0.unmanagedClasspathExistenceCheck","cat":"job","ts":5272314,"pid":1,"tid":5},
{"ph":"E","ts":5272468,"pid":1,"tid":4},
{"ph":"B","name":"side0.compileResources","cat":"job","ts":5272493,"pid":1,"tid":4},
{"ph":"E","ts":5272690,"pid":1,"tid":6},
{"ph":"B","name":"side0.mandatoryScalacOptions","cat":"job","ts":5272713,"pid":1,"tid":6},
{"ph":"E","ts":5272813,"pid":1,"tid":5},
{"ph":"B","name":"side0.scalacPluginMvnDeps","cat":"job","ts":5272838,"pid":1,"tid":5},
{"ph":"E","ts":5273063,"pid":1,"tid":4},
{"ph":"B","name":"side0.scalacOptions","cat":"job","ts":5273103,"pid":1,"tid":4},
{"ph":"E","ts":5273221,"pid":1,"tid":6},
{"ph":"E","ts":5273239,"pid":1,"tid":5},
{"ph":"B","name":"side0.zincAuxiliaryClassFileExtensions.super.javalib.JavaModule","cat":"job","ts":5273250,"pid":1,"tid":6},
{"ph":"B","name":"side0.jvmId","cat":"job","ts":5273282,"pid":1,"tid":5},
{"ph":"E","ts":5273720,"pid":1,"tid":4},
{"ph":"E","ts":5273741,"pid":1,"tid":5},
{"ph":"B","name":"side0.jvmIndexVersion","cat":"job","ts":5273749,"pid":1,"tid":4},
{"ph":"B","name":"side0.zincReportCachedProblems","cat":"job","ts":5273779,"pid":1,"tid":5},
{"ph":"E","ts":5273901,"pid":1,"tid":6},
{"ph":"B","name":"side1.scalaVersion","cat":"job","ts":5273929,"pid":1,"tid":6},
{"ph":"E","ts":5274318,"pid":1,"tid":5},
{"ph":"E","ts":5274339,"pid":1,"tid":4},
{"ph":"B","name":"side1.javacOptions","cat":"job","ts":5274344,"pid":1,"tid":5},
{"ph":"E","ts":5274399,"pid":1,"tid":6},
{"ph":"B","name":"side1.mandatoryJavacOptions","cat":"job","ts":5274419,"pid":1,"tid":4},
{"ph":"B","name":"side1.sources","cat":"job","ts":5274451,"pid":1,"tid":6},
{"ph":"E","ts":5274793,"pid":1,"tid":5},
{"ph":"B","name":"side1.generatedSources","cat":"job","ts":5274817,"pid":1,"tid":5},
{"ph":"E","ts":5274859,"pid":1,"tid":4},
{"ph":"B","name":"side1.wrappedSources","cat":"job","ts":5274881,"pid":1,"tid":4},
{"ph":"E","ts":5275247,"pid":1,"tid":5},
{"ph":"B","name":"side1.resolvedDepsWarnNonPlatform","cat":"job","ts":5275270,"pid":1,"tid":5},
{"ph":"E","ts":5275320,"pid":1,"tid":4},
{"ph":"B","name":"side1.platformSuffix","cat":"job","ts":5275359,"pid":1,"tid":4},
{"ph":"E","ts":5275839,"pid":1,"tid":4},
{"ph":"B","name":"side1.mvnDeps","cat":"job","ts":5275865,"pid":1,"tid":4},
{"ph":"E","ts":5275920,"pid":1,"tid":5},
{"ph":"B","name":"side1.mandatoryMvnDeps.super.javalib.JavaModule","cat":"job","ts":5275954,"pid":1,"tid":5},
{"ph":"E","ts":5276331,"pid":1,"tid":4},
{"ph":"B","name":"side1.compileMvnDeps","cat":"job","ts":5276361,"pid":1,"tid":4},
{"ph":"E","ts":5276545,"pid":1,"tid":5},
{"ph":"B","name":"side1.runMvnDeps","cat":"job","ts":5276571,"pid":1,"tid":5},
{"ph":"E","ts":5276945,"pid":1,"tid":5},
{"ph":"B","name":"side1.bomMvnDeps","cat":"job","ts":5276968,"pid":1,"tid":5},
{"ph":"E","ts":5277097,"pid":1,"tid":4},
{"ph":"B","name":"side1.depManagement","cat":"job","ts":5277256,"pid":1,"tid":4},
{"ph":"E","ts":5277317,"pid":1,"tid":5},
{"ph":"B","name":"side1.repositories","cat":"job","ts":5277348,"pid":1,"tid":5},
{"ph":"E","ts":5277780,"pid":1,"tid":5},
{"ph":"B","name":"side1.checkGradleModules","cat":"job","ts":5277808,"pid":1,"tid":5},
{"ph":"E","ts":5277863,"pid":1,"tid":4},
{"ph":"B","name":"side1.artifactTypes","cat":"job","ts":5277894,"pid":1,"tid":4},
{"ph":"E","ts":5278169,"pid":1,"tid":5},
{"ph":"B","name":"side1.unmanagedClasspath","cat":"job","ts":5278196,"pid":1,"tid":5},
{"ph":"E","ts":5278402,"pid":1,"tid":4},
{"ph":"B","name":"side1.unmanagedClasspathExistenceCheck","cat":"job","ts":5278429,"pid":1,"tid":4},
{"ph":"E","ts":5278532,"pid":1,"tid":5},
{"ph":"B","name":"side1.compileResources","cat":"job","ts":5278559,"pid":1,"tid":5},
{"ph":"E","ts":5278859,"pid":1,"tid":4},
{"ph":"B","name":"side1.mandatoryScalacOptions","cat":"job","ts":5278886,"pid":1,"tid":4},
{"ph":"E","ts":5278979,"pid":1,"tid":5},
{"ph":"B","name":"side1.scalacPluginMvnDeps","cat":"job","ts":5279001,"pid":1,"tid":5},
{"ph":"E","ts":5279256,"pid":1,"tid":4},
{"ph":"B","name":"side1.scalacOptions","cat":"job","ts":5279303,"pid":1,"tid":4},
{"ph":"E","ts":5279345,"pid":1,"tid":5},
{"ph":"B","name":"side1.zincAuxiliaryClassFileExtensions.super.javalib.JavaModule","cat":"job","ts":5279371,"pid":1,"tid":5},
{"ph":"E","ts":5279666,"pid":1,"tid":4},
{"ph":"B","name":"side1.jvmId","cat":"job","ts":5279692,"pid":1,"tid":4},
{"ph":"E","ts":5279841,"pid":1,"tid":5},
{"ph":"B","name":"side1.jvmIndexVersion","cat":"job","ts":5279863,"pid":1,"tid":5},
{"ph":"E","ts":5280050,"pid":1,"tid":4},
{"ph":"B","name":"side1.zincReportCachedProblems","cat":"job","ts":5280071,"pid":1,"tid":4},
{"ph":"E","ts":5280172,"pid":1,"tid":5},
{"ph":"B","name":"side2.scalaVersion","cat":"job","ts":5280193,"pid":1,"tid":5},
{"ph":"E","ts":5280409,"pid":1,"tid":4},
{"ph":"B","name":"side2.javacOptions","cat":"job","ts":5280429,"pid":1,"tid":4},
{"ph":"E","ts":5280541,"pid":1,"tid":5},
{"ph":"B","name":"side2.mandatoryJavacOptions","cat":"job","ts":5280564,"pid":1,"tid":5},
{"ph":"E","ts":5280765,"pid":1,"tid":4},
{"ph":"B","name":"side2.sources","cat":"job","ts":5280786,"pid":1,"tid":4},
{"ph":"E","ts":5280892,"pid":1,"tid":5},
{"ph":"B","name":"side2.generatedSources","cat":"job","ts":5280912,"pid":1,"tid":5},
{"ph":"E","ts":5281232,"pid":1,"tid":5},
{"ph":"B","name":"side2.wrappedSources","cat":"job","ts":5281254,"pid":1,"tid":5},
{"ph":"E","ts":5281612,"pid":1,"tid":5},
{"ph":"B","name":"side2.resolvedDepsWarnNonPlatform","cat":"job","ts":5281633,"pid":1,"tid":5},
{"ph":"E","ts":5282183,"pid":1,"tid":5},
{"ph":"B","name":"side2.platformSuffix","cat":"job","ts":5282221,"pid":1,"tid":5},
{"ph":"E","ts":5282511,"pid":1,"tid":2},
{"ph":"B","name":"side2.mvnDeps","cat":"job","ts":5282536,"pid":1,"tid":2},
{"ph":"E","ts":5282639,"pid":1,"tid":5},
{"ph":"B","name":"side2.mandatoryMvnDeps.super.javalib.JavaModule","cat":"job","ts":5282662,"pid":1,"tid":5},
{"ph":"E","ts":5282931,"pid":1,"tid":2},
{"ph":"B","name":"side2.compileMvnDeps","cat":"job","ts":5282952,"pid":1,"tid":2},
{"ph":"E","ts":5283348,"pid":1,"tid":5},
{"ph":"B","name":"side2.runMvnDeps","cat":"job","ts":5283385,"pid":1,"tid":5},
{"ph":"E","ts":5283447,"pid":1,"tid":2},
{"ph":"B","name":"side2.bomMvnDeps","cat":"job","ts":5283476,"pid":1,"tid":2},
{"ph":"E","ts":5283953,"pid":1,"tid":2},
{"ph":"E","ts":5283983,"pid":1,"tid":5},
{"ph":"B","name":"side2.depManagement","cat":"job","ts":5283993,"pid":1,"tid":2},
{"ph":"B","name":"side2.repositories","cat":"job","ts":5284016,"pid":1,"tid":5},
{"ph":"E","ts":5284479,"pid":1,"tid":5},
{"ph":"B","name":"side2.checkGradleModules","cat":"job","ts":5284504,"pid":1,"tid":5},
{"ph":"E","ts":5284544,"pid":1,"tid":2},
{"ph":"B","name":"side2.artifactTypes","cat":"job","ts":5284564,"pid":1,"tid":2},
{"ph":"E","ts":5284913,"pid":1,"tid":5},
{"ph":"B","name":"side2.unmanagedClasspath","cat":"job","ts":5284937,"pid":1,"tid":5},
{"ph":"E","ts":5285032,"pid":1,"tid":2},
{"ph":"B","name":"side2.unmanagedClasspathExistenceCheck","cat":"job","ts":5285054,"pid":1,"tid":2},
{"ph":"E","ts":5285355,"pid":1,"tid":5},
{"ph":"B","name":"side2.compileResources","cat":"job","ts":5285375,"pid":1,"tid":5},
{"ph":"E","ts":5285432,"pid":1,"tid":2},
{"ph":"B","name":"side2.mandatoryScalacOptions","cat":"job","ts":5285451,"pid":1,"tid":2},
{"ph":"E","ts":5285839,"pid":1,"tid":2},
{"ph":"E","ts":5285862,"pid":1,"tid":5},
{"ph":"B","name":"side2.scalacPluginMvnDeps","cat":"job","ts":5285870,"pid":1,"tid":2},
{"ph":"B","name":"side2.scalacOptions","cat":"job","ts":5285921,"pid":1,"tid":5},
{"ph":"E","ts":5286202,"pid":1,"tid":2},
{"ph":"B","name":"side2.zincAuxiliaryClassFileExtensions.super.javalib.JavaModule","cat":"job","ts":5286232,"pid":1,"tid":2},
{"ph":"E","ts":5286282,"pid":1,"tid":5},
{"ph":"B","name":"side2.jvmId","cat":"job","ts":5286305,"pid":1,"tid":5},
{"ph":"E","ts":5286691,"pid":1,"tid":2},
{"ph":"B","name":"side2.jvmIndexVersion","cat":"job","ts":5286713,"pid":1,"tid":2},
{"ph":"E","ts":5286740,"pid":1,"tid":5},
{"ph":"B","name":"side2.zincReportCachedProblems","cat":"job","ts":5286761,"pid":1,"tid":5},
{"ph":"E","ts":5287043,"pid":1,"tid":2},
{"ph":"B","name":"side3.scalaVersion","cat":"job","ts":5287079,"pid":1,"tid":2},
{"ph":"E","ts":5287134,"pid":1,"tid":5},
{"ph":"B","name":"side3.javacOptions","cat":"job","ts":5287153,"pid":1,"tid":5},
{"ph":"E","ts":5287283,"pid":1,"tid":6},
{"ph":"B","name":"side3.mandatoryJavacOptions","cat":"job","ts":5287325,"pid":1,"tid":6},
{"ph":"E","ts":5287450,"pid":1,"tid":2},
{"ph":"B","name":"side3.sources","cat":"job","ts":5287476,"pid":1,"tid":2},
{"ph":"E","ts":5287540,"pid":1,"tid":5},
{"ph":"B","name":"side3.generatedSources","cat":"job","ts":5287568,"pid":1,"tid":5},
{"ph":"E","ts":5287775,"pid":1,"tid":6},
{"ph":"B","name":"side3.wrappedSources","cat":"job","ts":5287802,"pid":1,"tid":6},
{"ph":"E","ts":5288052,"pid":1,"tid":5},
{"ph":"B","name":"side3.resolvedDepsWarnNonPlatform","cat":"job","ts":5288078,"pid":1,"tid":5},
{"ph":"E","ts":5288164,"pid":1,"tid":6},
{"ph":"B","name":"side3.platformSuffix","cat":"job","ts":5288190,"pid":1,"tid":6},
{"ph":"E","ts":5288521,"pid":1,"tid":5},
{"ph":"E","ts":5288549,"pid":1,"tid":6},
{"ph":"B","name":"side3.mvnDeps","cat":"job","ts":5288561,"pid":1,"tid":5},
{"ph":"B","name":"side3.mandatoryMvnDeps.super.javalib.JavaModule","cat":"job","ts":5288591,"pid":1,"tid":6},
{"ph":"E","ts":5289110,"pid":1,"tid":5},
{"ph":"B","name":"side3.compileMvnDeps","cat":"job","ts":5289137,"pid":1,"tid":5},
{"ph":"E","ts":5289241,"pid":1,"tid":6},
{"ph":"B","name":"side3.runMvnDeps","cat":"job","ts":5289272,"pid":1,"tid":6},
{"ph":"E","ts":5289538,"pid":1,"tid":5},
{"ph":"B","name":"side3.bomMvnDeps","cat":"job","ts":5289564,"pid":1,"tid":5},
{"ph":"E","ts":5289805,"pid":1,"tid":6},
{"ph":"B","name":"side3.depManagement","cat":"job","ts":5289835,"pid":1,"tid":6},
{"ph":"E","ts":5289923,"pid":1,"tid":5},
{"ph":"B","name":"side3.repositories","cat":"job","ts":5289948,"pid":1,"tid":5},
{"ph":"E","ts":5290280,"pid":1,"tid":6},
{"ph":"E","ts":5290313,"pid":1,"tid":5},
{"ph":"B","name":"side3.checkGradleModules","cat":"job","ts":5290334,"pid":1,"tid":6},
{"ph":"B","name":"side3.artifactTypes","cat":"job","ts":5290387,"pid":1,"tid":5},
{"ph":"E","ts":5290770,"pid":1,"tid":6},
{"ph":"B","name":"side3.unmanagedClasspath","cat":"job","ts":5290796,"pid":1,"tid":6},
{"ph":"E","ts":5290953,"pid":1,"tid":5},
{"ph":"B","name":"side3.unmanagedClasspathExistenceCheck","cat":"job","ts":5290978,"pid":1,"tid":5},
{"ph":"E","ts":5291226,"pid":1,"tid":6},
{"ph":"B","name":"side3.compileResources","cat":"job","ts":5291258,"pid":1,"tid":6},
{"ph":"E","ts":5291382,"pid":1,"tid":5},
{"ph":"B","name":"side3.mandatoryScalacOptions","cat":"job","ts":5291406,"pid":1,"tid":5},
{"ph":"E","ts":5291745,"pid":1,"tid":4},
{"ph":"B","name":"side3.scalacPluginMvnDeps","cat":"job","ts":5291775,"pid":1,"tid":4},
{"ph":"E","ts":5291868,"pid":1,"tid":6},
{"ph":"E","ts":5291895,"pid":1,"tid":5},
{"ph":"B","name":"side3.scalacOptions","cat":"job","ts":5291908,"pid":1,"tid":6},
{"ph":"B","name":"side3.zincAuxiliaryClassFileExtensions.super.javalib.JavaModule","cat":"job","ts":5292000,"pid":1,"tid":5},
{"ph":"E","ts":5292200,"pid":1,"tid":4},
{"ph":"B","name":"side3.jvmId","cat":"job","ts":5292226,"pid":1,"tid":4},
{"ph":"E","ts":5292271,"pid":1,"tid":6},
{"ph":"B","name":"side3.jvmIndexVersion","cat":"job","ts":5292289,"pid":1,"tid":6},
{"ph":"E","ts":5292572,"pid":1,"tid":4},
{"ph":"B","name":"side3.zincReportCachedProblems","cat":"job","ts":5292594,"pid":1,"tid":4},
{"ph":"E","ts":5292667,"pid":1,"tid":6},
{"ph":"B","name":"side4.scalaVersion","cat":"job","ts":5292718,"pid":1,"tid":6},
{"ph":"E","ts":5292800,"pid":1,"tid":5},
{"ph":"B","name":"side4.javacOptions","cat":"job","ts":5292826,"pid":1,"tid":5},
{"ph":"E","ts":5292956,"pid":1,"tid":4},
{"ph":"B","name":"side4.mandatoryJavacOptions","cat":"job","ts":5292977,"pid":1,"tid":4},
{"ph":"E","ts":5293306,"pid":1,"tid":5},
{"ph":"E","ts":5293327,"pid":1,"tid":6},
{"ph":"E","ts":5293356,"pid":1,"tid":4},
{"ph":"B","name":"side4.generatedSources","cat":"job","ts":5293365,"pid":1,"tid":6},
{"ph":"B","name":"side4.sources","cat":"job","ts":5293395,"pid":1,"tid":5},
{"ph":"B","name":"side4.wrappedSources","cat":"job","ts":5293419,"pid":1,"tid":4},
{"ph":"E","ts":5293890,"pid":1,"tid":4},
{"ph":"E","ts":5293906,"pid":1,"tid":6},
{"ph":"B","name":"side4.platformSuffix","cat":"job","ts":5293973,"pid":1,"tid":6},
{"ph":"B","name":"side4.resolvedDepsWarnNonPlatform","cat":"job","ts":5293999,"pid":1,"tid":4},
{"ph":"E","ts":5294474,"pid":1,"tid":4},
{"ph":"E","ts":5294508,"pid":1,"tid":6},
{"ph":"B","name":"side4.mvnDeps","cat":"job","ts":5294523,"pid":1,"tid":4},
{"ph":"B","name":"side4.mandatoryMvnDeps.super.javalib.JavaModule","cat":"job","ts":5294567,"pid":1,"tid":6},
{"ph":"E","ts":5294982,"pid":1,"tid":4},
{"ph":"B","name":"side4.compileMvnDeps","cat":"job","ts":5295009,"pid":1,"tid":4},
{"ph":"E","ts":5295124,"pid":1,"tid":6},
{"ph":"B","name":"side4.runMvnDeps","cat":"job","ts":5295151,"pid":1,"tid":6},
{"ph":"E","ts":5295379,"pid":1,"tid":4},
{"ph":"B","name":"side4.bomMvnDeps","cat":"job","ts":5295400,"pid":1,"tid":4},
{"ph":"E","ts":5295478,"pid":1,"tid":6},
{"ph":"B","name":"side4.depManagement","cat":"job","ts":5295497,"pid":1,"tid":6},
{"ph":"E","ts":5295741,"pid":1,"tid":4},
{"ph":"B","name":"side4.repositories","cat":"job","ts":5295771,"pid":1,"tid":4},
{"ph":"E","ts":5295814,"pid":1,"tid":6},
{"ph":"B","name":"side4.checkGradleModules","cat":"job","ts":5295847,"pid":1,"tid":6},
{"ph":"E","ts":5296142,"pid":1,"tid":4},
{"ph":"B","name":"side4.artifactTypes","cat":"job","ts":5296164,"pid":1,"tid":4},
{"ph":"E","ts":5296186,"pid":1,"tid":2},
{"ph":"B","name":"side4.unmanagedClasspath","cat":"job","ts":5296210,"pid":1,"tid":2},
{"ph":"E","ts":5296254,"pid":1,"tid":6},
{"ph":"B","name":"side4.unmanagedClasspathExistenceCheck","cat":"job","ts":5296293,"pid":1,"tid":6},
{"ph":"E","ts":5296551,"pid":1,"tid":2},
{"ph":"E","ts":5296590,"pid":1,"tid":4},
{"ph":"B","name":"side4.compileResources","cat":"job","ts":5296613,"pid":1,"tid":2},
{"ph":"B","name":"side4.mandatoryScalacOptions","cat":"job","ts":5296693,"pid":1,"tid":4},
{"ph":"E","ts":5296737,"pid":1,"tid":6},
{"ph":"B","name":"side4.scalacPluginMvnDeps","cat":"job","ts":5296765,"pid":1,"tid":6},
{"ph":"E","ts":5297098,"pid":1,"tid":6},
{"ph":"E","ts":5297110,"pid":1,"tid":4},
{"ph":"B","name":"side4.scalacOptions","cat":"job","ts":5297128,"pid":1,"tid":6},
{"ph":"B","name":"side4.zincAuxiliaryClassFileExtensions.super.javalib.JavaModule","cat":"job","ts":5297152,"pid":1,"tid":4},
{"ph":"E","ts":5297224,"pid":1,"tid":2},
{"ph":"B","name":"side4.jvmId","cat":"job","ts":5297274,"pid":1,"tid":2},
{"ph":"E","ts":5297447,"pid":1,"tid":6},
{"ph":"B","name":"side4.jvmIndexVersion","cat":"job","ts":5297470,"pid":1,"tid":6},
{"ph":"E","ts":5297615,"pid":1,"tid":2},
{"ph":"B","name":"side4.zincReportCachedProblems","cat":"job","ts":5297641,"pid":1,"tid":2},
{"ph":"E","ts":5297726,"pid":1,"tid":4},
{"ph":"B","name":"side5.scalaVersion","cat":"job","ts":5297747,"pid":1,"tid":4},
{"ph":"E","ts":5297823,"pid":1,"tid":6},
{"ph":"B","name":"side5.javacOptions","cat":"job","ts":5297851,"pid":1,"tid":6},
{"ph":"E","ts":5297966,"pid":1,"tid":2},
{"ph":"B","name":"side5.mandatoryJavacOptions","cat":"job","ts":5297991,"pid":1,"tid":2},
{"ph":"E","ts":5298212,"pid":1,"tid":6},
{"ph":"E","ts":5298234,"pid":1,"tid":4},
{"ph":"B","name":"side5.sources","cat":"job","ts":5298255,"pid":1,"tid":6},
{"ph":"B","name":"side5.generatedSources","cat":"job","ts":5298289,"pid":1,"tid":4},
{"ph":"E","ts":5298333,"pid":1,"tid":2},
{"ph":"B","name":"side5.wrappedSources","cat":"job","ts":5298358,"pid":1,"tid":2},
{"ph":"E","ts":5298733,"pid":1,"tid":4},
{"ph":"E","ts":5298753,"pid":1,"tid":2},
{"ph":"B","name":"side5.resolvedDepsWarnNonPlatform","cat":"job","ts":5298763,"pid":1,"tid":4},
{"ph":"B","name":"side5.platformSuffix","cat":"job","ts":5298817,"pid":1,"tid":2},
{"ph":"E","ts":5299157,"pid":1,"tid":4},
{"ph":"B","name":"side5.mvnDeps","cat":"job","ts":5299185,"pid":1,"tid":4},
{"ph":"E","ts":5299230,"pid":1,"tid":2},
{"ph":"B","name":"side5.mandatoryMvnDeps.super.javalib.JavaModule","cat":"job","ts":5299262,"pid":1,"tid":2},
{"ph":"E","ts":5301565,"pid":1,"tid":4},
{"ph":"B","name":"side5.compileMvnDeps","cat":"job","ts":5301603,"pid":1,"tid":4},
{"ph":"E","ts":5301757,"pid":1,"tid":2},
{"ph":"B","name":"side5.runMvnDeps","cat":"job","ts":5301784,"pid":1,"tid":2},
{"ph":"E","ts":5302118,"pid":1,"tid":4},
{"ph":"E","ts":5302136,"pid":1,"tid":2},
{"ph":"B","name":"side5.bomMvnDeps","cat":"job","ts":5302139,"pid":1,"tid":4},
{"ph":"B","name":"side5.depManagement","cat":"job","ts":5302155,"pid":1,"tid":2},
{"ph":"E","ts":5302480,"pid":1,"tid":2},
{"ph":"B","name":"side5.repositories","cat":"job","ts":5302504,"pid":1,"tid":2},
{"ph":"E","ts":5302762,"pid":1,"tid":4},
{"ph":"B","name":"side5.checkGradleModules","cat":"job","ts":5302795,"pid":1,"tid":4},
{"ph":"E","ts":5302866,"pid":1,"tid":2},
{"ph":"B","name":"side5.artifactTypes","cat":"job","ts":5302897,"pid":1,"tid":2},
{"ph":"E","ts":5303221,"pid":1,"tid":4},
{"ph":"B","name":"side5.unmanagedClasspath","cat":"job","ts":5303250,"pid":1,"tid":4},
{"ph":"E","ts":5303367,"pid":1,"tid":2},
{"ph":"B","name":"side5.unmanagedClasspathExistenceCheck","cat":"job","ts":5303393,"pid":1,"tid":2},
{"ph":"E","ts":5303637,"pid":1,"tid":4},
{"ph":"B","name":"side5.compileResources","cat":"job","ts":5303663,"pid":1,"tid":4},
{"ph":"E","ts":5303760,"pid":1,"tid":2},
{"ph":"B","name":"side5.mandatoryScalacOptions","cat":"job","ts":5303791,"pid":1,"tid":2},
{"ph":"E","ts":5303978,"pid":1,"tid":5},
{"ph":"B","name":"side5.scalacPluginMvnDeps","cat":"job","ts":5304005,"pid":1,"tid":5},
{"ph":"E","ts":5304193,"pid":1,"tid":2},
{"ph":"E","ts":5304219,"pid":1,"tid":4},
{"ph":"B","name":"side5.scalacOptions","cat":"job","ts":5304232,"pid":1,"tid":2},
{"ph":"B","name":"side5.zincAuxiliaryClassFileExtensions.super.javalib.JavaModule","cat":"job","ts":5304286,"pid":1,"tid":4},
{"ph":"E","ts":5304342,"pid":1,"tid":5},
{"ph":"B","name":"side5.jvmId","cat":"job","ts":5304368,"pid":1,"tid":5},
{"ph":"E","ts":5304629,"pid":1,"tid":2},
{"ph":"B","name":"side5.jvmIndexVersion","cat":"job","ts":5304649,"pid":1,"tid":2},
{"ph":"E","ts":5304720,"pid":1,"tid":5},
{"ph":"B","name":"side5.zincReportCachedProblems","cat":"job","ts":5304738,"pid":1,"tid":5},
{"ph":"E","ts":5304939,"pid":1,"tid":4},
{"ph":"B","name":"side6.scalaVersion","cat":"job","ts":5304965,"pid":1,"tid":4},
{"ph":"E","ts":5305000,"pid":1,"tid":2},
{"ph":"E","ts":5305031,"pid":1,"tid":5},
{"ph":"B","name":"side6.mandatoryJavacOptions","cat":"job","ts":5305054,"pid":1,"tid":5},
{"ph":"B","name":"side6.javacOptions","cat":"job","ts":5305084,"pid":1,"tid":2},
{"ph":"E","ts":5305531,"pid":1,"tid":2},
{"ph":"E","ts":5305544,"pid":1,"tid":4},
{"ph":"E","ts":5305564,"pid":1,"tid":5},
{"ph":"B","name":"side6.generatedSources","cat":"job","ts":5305581,"pid":1,"tid":4},
{"ph":"B","name":"side6.sources","cat":"job","ts":5305613,"pid":1,"tid":2},
{"ph":"B","name":"side6.wrappedSources","cat":"job","ts":5305635,"pid":1,"tid":5},
{"ph":"E","ts":5306089,"pid":1,"tid":5},
{"ph":"B","name":"side6.resolvedDepsWarnNonPlatform","cat":"job","ts":5306115,"pid":1,"tid":5},
{"ph":"E","ts":5306164,"pid":1,"tid":4},
{"ph":"B","name":"side6.platformSuffix","cat":"job","ts":5306184,"pid":1,"tid":4},
{"ph":"E","ts":5306485,"pid":1,"tid":4},
{"ph":"B","name":"side6.mvnDeps","cat":"job","ts":5306520,"pid":1,"tid":4},
{"ph":"E","ts":5306586,"pid":1,"tid":5},
{"ph":"B","name":"side6.mandatoryMvnDeps.super.javalib.JavaModule","cat":"job","ts":5306626,"pid":1,"tid":5},
{"ph":"E","ts":5306861,"pid":1,"tid":4},
{"ph":"B","name":"side6.compileMvnDeps","cat":"job","ts":5306886,"pid":1,"tid":4},
{"ph":"E","ts":5307347,"pid":1,"tid":4},
{"ph":"E","ts":5307379,"pid":1,"tid":5},
{"ph":"B","name":"side6.runMvnDeps","cat":"job","ts":5307387,"pid":1,"tid":4},
{"ph":"B","name":"side6.bomMvnDeps","cat":"job","ts":5307412,"pid":1,"tid":5},
{"ph":"E","ts":5307813,"pid":1,"tid":4},
{"ph":"E","ts":5307830,"pid":1,"tid":5},
{"ph":"B","name":"side6.depManagement","cat":"job","ts":5307837,"pid":1,"tid":4},
{"ph":"B","name":"side6.repositories","cat":"job","ts":5307857,"pid":1,"tid":5},
{"ph":"E","ts":5308283,"pid":1,"tid":4},
{"ph":"E","ts":5308304,"pid":1,"tid":5},
{"ph":"B","name":"side6.artifactTypes","cat":"job","ts":5308334,"pid":1,"tid":5},
{"ph":"B","name":"side6.checkGradleModules","cat":"job","ts":5308371,"pid":1,"tid":4},
{"ph":"E","ts":5308741,"pid":1,"tid":4},
{"ph":"E","ts":5308769,"pid":1,"tid":5},
{"ph":"B","name":"side6.unmanagedClasspath","cat":"job","ts":5308780,"pid":1,"tid":4},
{"ph":"B","name":"side6.unmanagedClasspathExistenceCheck","cat":"job","ts":5308798,"pid":1,"tid":5},
{"ph":"E","ts":5309222,"pid":1,"tid":4},
{"ph":"E","ts":5309239,"pid":1,"tid":5},
{"ph":"E","ts":5309246,"pid":1,"tid":6},
{"ph":"B","name":"side6.compileResources","cat":"job","ts":5309251,"pid":1,"tid":4},
{"ph":"B","name":"side6.mandatoryScalacOptions","cat":"job","ts":5309270,"pid":1,"tid":5},
{"ph":"B","name":"side6.scalacPluginMvnDeps","cat":"job","ts":5309317,"pid":1,"tid":6},
{"ph":"E","ts":5309651,"pid":1,"tid":5},
{"ph":"B","name":"side6.scalacOptions","cat":"job","ts":5309674,"pid":1,"tid":5},
{"ph":"E","ts":5310051,"pid":1,"tid":6},
{"ph":"E","ts":5310071,"pid":1,"tid":5},
{"ph":"B","name":"side6.zincAuxiliaryClassFileExtensions.super.javalib.JavaModule","cat":"job","ts":5310075,"pid":1,"tid":6},
{"ph":"B","name":"side6.jvmId","cat":"job","ts":5310174,"pid":1,"tid":5},
{"ph":"E","ts":5310242,"pid":1,"tid":4},
{"ph":"B","name":"side6.jvmIndexVersion","cat":"job","ts":5310283,"pid":1,"tid":4},
{"ph":"E","ts":5310541,"pid":1,"tid":6},
{"ph":"B","name":"side6.zincReportCachedProblems","cat":"job","ts":5310577,"pid":1,"tid":6},
{"ph":"E","ts":5310788,"pid":1,"tid":5},
{"ph":"B","name":"side7.scalaVersion","cat":"job","ts":5310823,"pid":1,"tid":5},
{"ph":"E","ts":5310881,"pid":1,"tid":4},
{"ph":"B","name":"side7.javacOptions","cat":"job","ts":5310905,"pid":1,"tid":4},
{"ph":"E","ts":5310933,"pid":1,"tid":6},
{"ph":"B","name":"side7.mandatoryJavacOptions","cat":"job","ts":5310963,"pid":1,"tid":6},
{"ph":"E","ts":5311331,"pid":1,"tid":5},
{"ph":"E","ts":5311340,"pid":1,"tid":4},
{"ph":"E","ts":5311367,"pid":1,"tid":6},
{"ph":"B","name":"side7.generatedSources","cat":"job","ts":5311377,"pid":1,"tid":5},
{"ph":"B","name":"side7.sources","cat":"job","ts":5311398,"pid":1,"tid":4},
{"ph":"B","name":"side7.wrappedSources","cat":"job","ts":5311421,"pid":1,"tid":6},
{"ph":"E","ts":5311778,"pid":1,"tid":5},
{"ph":"B","name":"side7.resolvedDepsWarnNonPlatform","cat":"job","ts":5311801,"pid":1,"tid":5},
{"ph":"E","ts":5311852,"pid":1,"tid":6},
{"ph":"B","name":"side7.platformSuffix","cat":"job","ts":5311877,"pid":1,"tid":6},
{"ph":"E","ts":5312127,"pid":1,"tid":5},
{"ph":"B","name":"side7.mvnDeps","cat":"job","ts":5312150,"pid":1,"tid":5},
{"ph":"E","ts":5312207,"pid":1,"tid":6},
{"ph":"B","name":"side7.mandatoryMvnDeps.super.javalib.JavaModule","cat":"job","ts":5312232,"pid":1,"tid":6},
{"ph":"E","ts":5312464,"pid":1,"tid":5},
{"ph":"B","name":"side7.compileMvnDeps","cat":"job","ts":5312487,"pid":1,"tid":5},
{"ph":"E","ts":5312753,"pid":1,"tid":6},
{"ph":"B","name":"side7.runMvnDeps","cat":"job","ts":5312775,"pid":1,"tid":6},
{"ph":"E","ts":5312882,"pid":1,"tid":5},
{"ph":"B","name":"side7.bomMvnDeps","cat":"job","ts":5312902,"pid":1,"tid":5},
{"ph":"E","ts":5313141,"pid":1,"tid":6},
{"ph":"B","name":"side7.depManagement","cat":"job","ts":5313162,"pid":1,"tid":6},
{"ph":"E","ts":5313283,"pid":1,"tid":5},
{"ph":"B","name":"side7.repositories","cat":"job","ts":5313304,"pid":1,"tid":5},
{"ph":"E","ts":5313481,"pid":1,"tid":6},
{"ph":"B","name":"side7.checkGradleModules","cat":"job","ts":5313503,"pid":1,"tid":6},
{"ph":"E","ts":5313707,"pid":1,"tid":5},
{"ph":"B","name":"side7.artifactTypes","cat":"job","ts":5313729,"pid":1,"tid":5},
{"ph":"E","ts":5313828,"pid":1,"tid":6},
{"ph":"B","name":"side7.unmanagedClasspath","cat":"job","ts":5313861,"pid":1,"tid":6},
{"ph":"E","ts":5314153,"pid":1,"tid":5},
{"ph":"B","name":"side7.unmanagedClasspathExistenceCheck","cat":"job","ts":5314172,"pid":1,"tid":5},
{"ph":"E","ts":5314316,"pid":1,"tid":6},
{"ph":"B","name":"side7.compileResources","cat":"job","ts":5314338,"pid":1,"tid":6},
{"ph":"E","ts":5314582,"pid":1,"tid":5},
{"ph":"B","name":"side7.mandatoryScalacOptions","cat":"job","ts":5314610,"pid":1,"tid":5},
{"ph":"E","ts":5314651,"pid":1,"tid":2},
{"ph":"B","name":"side7.scalacPluginMvnDeps","cat":"job","ts":5314676,"pid":1,"tid":2},
{"ph":"E","ts":5314780,"pid":1,"tid":6},
{"ph":"B","name":"side7.scalacOptions","cat":"job","ts":5314800,"pid":1,"tid":6},
{"ph":"E","ts":5315032,"pid":1,"tid":5},
{"ph":"B","name":"side7.zincAuxiliaryClassFileExtensions.super.javalib.JavaModule","cat":"job","ts":5315055,"pid":1,"tid":5},
{"ph":"E","ts":5315137,"pid":1,"tid":2},
{"ph":"E","ts":5315155,"pid":1,"tid":6},
{"ph":"B","name":"side7.jvmId","cat":"job","ts":5315160,"pid":1,"tid":2},
{"ph":"B","name":"side7.jvmIndexVersion","cat":"job","ts":5315178,"pid":1,"tid":6},
{"ph":"E","ts":5315592,"pid":1,"tid":6},
{"ph":"B","name":"side7.zincReportCachedProblems","cat":"job","ts":5315610,"pid":1,"tid":6},
{"ph":"E","ts":5315644,"pid":1,"tid":2},
{"ph":"E","ts":5315654,"pid":1,"tid":5},
{"ph":"E","ts":5315955,"pid":1,"tid":6},
{"ph":"B","name":"common.scalaLibraryMvnDeps","cat":"job","ts":5317766,"pid":1,"tid":2},
{"ph":"B","name":"common.jvmVersion","cat":"job","ts":5317896,"pid":1,"tid":5},
{"ph":"B","name":"chain0.scalaLibraryMvnDeps","cat":"job","ts":5317917,"pid":1,"tid":6},
{"ph":"E","ts":5318859,"pid":1,"tid":5},
{"ph":"B","name":"chain0.jvmVersion","cat":"job","ts":5318946,"pid":1,"tid":5},
{"ph":"E","ts":5319375,"pid":1,"tid":5},
{"ph":"B","name":"chain1.scalaLibraryMvnDeps","cat":"job","ts":5319401,"pid":1,"tid":5},
{"ph":"E","ts":5320273,"pid":1,"tid":4},
{"ph":"B","name":"chain1.jvmVersion","cat":"job","ts":5320328,"pid":1,"tid":4},
{"ph":"E","ts":5320697,"pid":1,"tid":4},
{"ph":"B","name":"chain2.scalaLibraryMvnDeps","cat":"job","ts":5320724,"pid":1,"tid":4},
{"ph":"E","ts":5331869,"pid":1,"tid":5},
{"ph":"E","ts":5331881,"pid":1,"tid":4},
{"ph":"E","ts":5331888,"pid":1,"tid":2},
{"ph":"E","ts":5331913,"pid":1,"tid":6},
{"ph":"B","name":"chain2.jvmVersion","cat":"job","ts":5331925,"pid":1,"tid":5},
{"ph":"B","name":"chain3.jvmVersion","cat":"job","ts":5331962,"pid":1,"tid":4},
{"ph":"B","name":"chain3.scalaLibraryMvnDeps","cat":"job","ts":5331984,"pid":1,"tid":2},
{"ph":"B","name":"side0.scalaLibraryMvnDeps","cat":"job","ts":5332027,"pid":1,"tid":6},
{"ph":"E","ts":5332552,"pid":1,"tid":4},
{"ph":"B","name":"side0.jvmVersion","cat":"job","ts":5332584,"pid":1,"tid":4},
{"ph":"E","ts":5332628,"pid":1,"tid":5},
{"ph":"B","name":"side1.scalaLibraryMvnDeps","cat":"job","ts":5332667,"pid":1,"tid":5},
{"ph":"E","ts":5332715,"pid":1,"tid":6},
{"ph":"B","name":"side1.jvmVersion","cat":"job","ts":5332755,"pid":1,"tid":6},
{"ph":"E","ts":5332812,"pid":1,"tid":2},
{"ph":"B","name":"side2.scalaLibraryMvnDeps","cat":"job","ts":5332840,"pid":1,"tid":2},
{"ph":"E","ts":5332965,"pid":1,"tid":4},
{"ph":"B","name":"side2.jvmVersion","cat":"job","ts":5332999,"pid":1,"tid":4},
{"ph":"E","ts":5333096,"pid":1,"tid":6},
{"ph":"B","name":"side3.scalaLibraryMvnDeps","cat":"job","ts":5333126,"pid":1,"tid":6},
{"ph":"E","ts":5333254,"pid":1,"tid":5},
{"ph":"B","name":"side3.jvmVersion","cat":"job","ts":5333293,"pid":1,"tid":5},
{"ph":"E","ts":5333323,"pid":1,"tid":2},
{"ph":"B","name":"side4.scalaLibraryMvnDeps","cat":"job","ts":5333355,"pid":1,"tid":2},
{"ph":"E","ts":5333384,"pid":1,"tid":4},
{"ph":"B","name":"side4.jvmVersion","cat":"job","ts":5333429,"pid":1,"tid":4},
{"ph":"E","ts":5333586,"pid":1,"tid":6},
{"ph":"B","name":"side5.scalaLibraryMvnDeps","cat":"job","ts":5333632,"pid":1,"tid":6},
{"ph":"E","ts":5333669,"pid":1,"tid":5},
{"ph":"B","name":"side5.jvmVersion","cat":"job","ts":5333724,"pid":1,"tid":5},
{"ph":"E","ts":5333793,"pid":1,"tid":4},
{"ph":"B","name":"side6.scalaLibraryMvnDeps","cat":"job","ts":5333815,"pid":1,"tid":4},
{"ph":"E","ts":5333894,"pid":1,"tid":2},
{"ph":"B","name":"side6.jvmVersion","cat":"job","ts":5333935,"pid":1,"tid":2},
{"ph":"E","ts":5334029,"pid":1,"tid":5},
{"ph":"B","name":"side7.scalaLibraryMvnDeps","cat":"job","ts":5334056,"pid":1,"tid":5},
{"ph":"E","ts":5334098,"pid":1,"tid":6},
{"ph":"B","name":"side7.jvmVersion","cat":"job","ts":5334151,"pid":1,"tid":6},
{"ph":"E","ts":5334237,"pid":1,"tid":2},
{"ph":"B","name":"common.zincAuxiliaryClassFileExtensions","cat":"job","ts":5334278,"pid":1,"tid":2},
{"ph":"E","ts":5334397,"pid":1,"tid":4},
{"ph":"B","name":"common.allSources","cat":"job","ts":5334436,"pid":1,"tid":4},
{"ph":"E","ts":5334514,"pid":1,"tid":5},
{"ph":"E","ts":5334535,"pid":1,"tid":6},
{"ph":"E","ts":5334595,"pid":1,"tid":2},
{"ph":"B","name":"chain0.zincAuxiliaryClassFileExtensions","cat":"job","ts":5334792,"pid":1,"tid":2},
{"ph":"B","name":"chain1.zincAuxiliaryClassFileExtensions","cat":"job","ts":5334817,"pid":1,"tid":6},
{"ph":"B","name":"chain0.allSources","cat":"job","ts":5334845,"pid":1,"tid":5},
{"ph":"E","ts":5334895,"pid":1,"tid":4},
{"ph":"B","name":"chain1.allSources","cat":"job","ts":5334923,"pid":1,"tid":4},
{"ph":"E","ts":5335125,"pid":1,"tid":2},
{"ph":"B","name":"chain2.zincAuxiliaryClassFileExtensions","cat":"job","ts":5335161,"pid":1,"tid":2},
{"ph":"E","ts":5335203,"pid":1,"tid":5},
{"ph":"E","ts":5335224,"pid":1,"tid":6},
{"ph":"B","name":"chain2.allSources","cat":"job","ts":5335238,"pid":1,"tid":5},
{"ph":"B","name":"chain3.zincAuxiliaryClassFileExtensions","cat":"job","ts":5335250,"pid":1,"tid":6},
{"ph":"E","ts":5335294,"pid":1,"tid":4},
{"ph":"B","name":"chain3.allSources","cat":"job","ts":5335327,"pid":1,"tid":4},
{"ph":"E","ts":5335464,"pid":1,"tid":2},
{"ph":"B","name":"side0.zincAuxiliaryClassFileExtensions","cat":"job","ts":5335493,"pid":1,"tid":2},
{"ph":"E","ts":5335596,"pid":1,"tid":6},
{"ph":"B","name":"side0.allSources","cat":"job","ts":5335618,"pid":1,"tid":6},
{"ph":"E","ts":5335685,"pid":1,"tid":5},
{"ph":"E","ts":5335708,"pid":1,"tid":4},
{"ph":"B","name":"side1.zincAuxiliaryClassFileExtensions","cat":"job","ts":5335741,"pid":1,"tid":5},
{"ph":"B","name":"side1.allSources","cat":"job","ts":5335765,"pid":1,"tid":4},
{"ph":"E","ts":5335807,"pid":1,"tid":2},
{"ph":"B","name":"side2.zincAuxiliaryClassFileExtensions","cat":"job","ts":5335839,"pid":1,"tid":2},
{"ph":"E","ts":5335949,"pid":1,"tid":6},
{"ph":"B","name":"side2.allSources","cat":"job","ts":5335975,"pid":1,"tid":6},
{"ph":"E","ts":5336153,"pid":1,"tid":4},
{"ph":"B","name":"side3.zincAuxiliaryClassFileExtensions","cat":"job","ts":5336185,"pid":1,"tid":4},
{"ph":"E","ts":5336213,"pid":1,"tid":2},
{"ph":"E","ts":5336249,"pid":1,"tid":5},
{"ph":"B","name":"side3.allSources","cat":"job","ts":5336259,"pid":1,"tid":2},
{"ph":"B","name":"side4.zincAuxiliaryClassFileExtensions","cat":"job","ts":5336291,"pid":1,"tid":5},
{"ph":"E","ts":5336370,"pid":1,"tid":6},
{"ph":"B","name":"side4.allSources","cat":"job","ts":5336395,"pid":1,"tid":6},
{"ph":"E","ts":5336589,"pid":1,"tid":4},
{"ph":"B","name":"side5.zincAuxiliaryClassFileExtensions","cat":"job","ts":5336613,"pid":1,"tid":4},
{"ph":"E","ts":5336774,"pid":1,"tid":5},
{"ph":"E","ts":5336792,"pid":1,"tid":6},
{"ph":"E","ts":5336801,"pid":1,"tid":2},
{"ph":"B","name":"side5.allSources","cat":"job","ts":5336806,"pid":1,"tid":5},
{"ph":"B","name":"side6.zincAuxiliaryClassFileExtensions","cat":"job","ts":5336825,"pid":1,"tid":2},
{"ph":"B","name":"side6.allSources","cat":"job","ts":5336849,"pid":1,"tid":6},
{"ph":"E","ts":5336936,"pid":1,"tid":4},
{"ph":"B","name":"side7.zincAuxiliaryClassFileExtensions","cat":"job","ts":5336966,"pid":1,"tid":4},
{"ph":"E","ts":5337265,"pid":1,"tid":2},
{"ph":"E","ts":5337282,"pid":1,"tid":6},
{"ph":"E","ts":5337291,"pid":1,"tid":5},
{"ph":"B","name":"mill.javalib.JvmWorkerModule/classpath","cat":"job","ts":5337333,"pid":1,"tid":6},
{"ph":"E","ts":5337370,"pid":1,"tid":4},
{"ph":"B","name":"common.localCompileClasspath","cat":"job","ts":5337488,"pid":1,"tid":4},
{"ph":"B","name":"chain0.localCompileClasspath","cat":"job","ts":5337550,"pid":1,"tid":5},
{"ph":"B","name":"side7.allSources","cat":"job","ts":5337578,"pid":1,"tid":2},
{"ph":"E","ts":5337973,"pid":1,"tid":2},
{"ph":"B","name":"chain1.localCompileClasspath","cat":"job","ts":5337999,"pid":1,"tid":2},
{"ph":"E","ts":5338025,"pid":1,"tid":4},
{"ph":"B","name":"chain1.mandatoryMvnDeps","cat":"job","ts":5338052,"pid":1,"tid":4},
{"ph":"E","ts":5338137,"pid":1,"tid":5},
{"ph":"B","name":"chain2.mandatoryMvnDeps","cat":"job","ts":5338162,"pid":1,"tid":5},
{"ph":"E","ts":5338378,"pid":1,"tid":2},
{"ph":"B","name":"common.mandatoryMvnDeps","cat":"job","ts":5338396,"pid":1,"tid":2},
{"ph":"E","ts":5338443,"pid":1,"tid":4},
{"ph":"B","name":"chain2.localCompileClasspath","cat":"job","ts":5338464,"pid":1,"tid":4},
{"ph":"E","ts":5338633,"pid":1,"tid":5},
{"ph":"B","name":"chain0.mandatoryMvnDeps","cat":"job","ts":5338658,"pid":1,"tid":5},
{"ph":"E","ts":5338864,"pid":1,"tid":4},
{"ph":"B","name":"chain3.localCompileClasspath","cat":"job","ts":5338887,"pid":1,"tid":4},
{"ph":"E","ts":5338923,"pid":1,"tid":2},
{"ph":"B","name":"side0.localCompileClasspath","cat":"job","ts":5338957,"pid":1,"tid":2},
{"ph":"E","ts":5339004,"pid":1,"tid":5},
{"ph":"B","name":"side0.mandatoryMvnDeps","cat":"job","ts":5339038,"pid":1,"tid":5},
{"ph":"E","ts":5339262,"pid":1,"tid":4},
{"ph":"E","ts":5339277,"pid":1,"tid":2},
{"ph":"B","name":"side1.localCompileClasspath","cat":"job","ts":5339287,"pid":1,"tid":4},
{"ph":"B","name":"chain3.mandatoryMvnDeps","cat":"job","ts":5339304,"pid":1,"tid":2},
{"ph":"E","ts":5339398,"pid":1,"tid":5},
{"ph":"B","name":"side0.javaHome","cat":"job","ts":5339417,"pid":1,"tid":5},
{"ph":"E","ts":5339655,"pid":1,"tid":4},
{"ph":"E","ts":5339662,"pid":1,"tid":2},
{"ph":"B","name":"side1.javaHome","cat":"job","ts":5339678,"pid":1,"tid":4},
{"ph":"B","name":"side2.localCompileClasspath","cat":"job","ts":5339709,"pid":1,"tid":2},
{"ph":"E","ts":5340000,"pid":1,"tid":2},
{"ph":"B","name":"side1.mandatoryMvnDeps","cat":"job","ts":5340021,"pid":1,"tid":2},
{"ph":"E","ts":5340334,"pid":1,"tid":2},
{"ph":"B","name":"side3.localCompileClasspath","cat":"job","ts":5340352,"pid":1,"tid":2},
{"ph":"E","ts":5340617,"pid":1,"tid":2},
{"ph":"B","name":"side2.mandatoryMvnDeps","cat":"job","ts":5340631,"pid":1,"tid":2},
{"ph":"E","ts":5340921,"pid":1,"tid":2},
{"ph":"B","name":"side2.javaHome","cat":"job","ts":5340939,"pid":1,"tid":2},
{"ph":"E","ts":5356153,"pid":1,"tid":4},
{"ph":"E","ts":5356174,"pid":1,"tid":5},
{"ph":"E","ts":5356195,"pid":1,"tid":2},
{"ph":"B","name":"side3.mandatoryMvnDeps","cat":"job","ts":5356210,"pid":1,"tid":5},
{"ph":"B","name":"side3.javaHome","cat":"job","ts":5356274,"pid":1,"tid":2},
{"ph":"B","name":"side4.localCompileClasspath","cat":"job","ts":5356299,"pid":1,"tid":4},
{"ph":"E","ts":5356853,"pid":1,"tid":4},
{"ph":"B","name":"side5.localCompileClasspath","cat":"job","ts":5356890,"pid":1,"tid":4},
{"ph":"E","ts":5356916,"pid":1,"tid":5},
{"ph":"B","name":"side4.javaHome","cat":"job","ts":5356939,"pid":1,"tid":5},
{"ph":"E","ts":5357330,"pid":1,"tid":4},
{"ph":"B","name":"side4.mandatoryMvnDeps","cat":"job","ts":5357365,"pid":1,"tid":4},
{"ph":"E","ts":5357670,"pid":1,"tid":2},
{"ph":"B","name":"side6.localCompileClasspath","cat":"job","ts":5357696,"pid":1,"tid":2},
{"ph":"E","ts":5357894,"pid":1,"tid":4},
{"ph":"B","name":"side5.javaHome","cat":"job","ts":5357920,"pid":1,"tid":4},
{"ph":"E","ts":5358038,"pid":1,"tid":5},
{"ph":"B","name":"side5.mandatoryMvnDeps","cat":"job","ts":5358066,"pid":1,"tid":5},
{"ph":"E","ts":5358105,"pid":1,"tid":2},
{"ph":"B","name":"side7.localCompileClasspath","cat":"job","ts":5358132,"pid":1,"tid":2},
{"ph":"E","ts":5358490,"pid":1,"tid":5},
{"ph":"E","ts":5358504,"pid":1,"tid":2},
{"ph":"B","name":"side6.javaHome","cat":"job","ts":5358519,"pid":1,"tid":5},
{"ph":"B","name":"side6.mandatoryMvnDeps","cat":"job","ts":5358546,"pid":1,"tid":2},
{"ph":"E","ts":5359011,"pid":1,"tid":2},
{"ph":"E","ts":5359048,"pid":1,"tid":4},
{"ph":"B","name":"side7.mandatoryMvnDeps","cat":"job","ts":5359065,"pid":1,"tid":2},
{"ph":"B","name":"side7.javaHome","cat":"job","ts":5359082,"pid":1,"tid":4},
{"ph":"E","ts":5359526,"pid":1,"tid":2},
{"ph":"B","name":"common.javaHome","cat":"job","ts":5359684,"pid":1,"tid":2},
{"ph":"E","ts":5359844,"pid":1,"tid":5},
{"ph":"B","name":"chain0.javaHome","cat":"job","ts":5359914,"pid":1,"tid":5},
{"ph":"E","ts":5360077,"pid":1,"tid":4},
{"ph":"B","name":"chain1.javaHome","cat":"job","ts":5360135,"pid":1,"tid":4},
{"ph":"E","ts":5360601,"pid":1,"tid":2},
{"ph":"B","name":"chain3.javaHome","cat":"job","ts":5360677,"pid":1,"tid":2},
{"ph":"E","ts":5360738,"pid":1,"tid":5},
{"ph":"B","name":"chain2.javaHome","cat":"job","ts":5360784,"pid":1,"tid":5},
{"ph":"E","ts":5360911,"pid":1,"tid":4},
{"ph":"B","name":"common.scalaCompilerBridge","cat":"job","ts":5361172,"pid":1,"tid":4},
{"ph":"E","ts":5361824,"pid":1,"tid":5},
{"ph":"E","ts":5361843,"pid":1,"tid":2},
{"ph":"B","name":"common.allSourceFiles","cat":"job","ts":5361984,"pid":1,"tid":2},
{"ph":"B","name":"chain0.allSourceFiles","cat":"job","ts":5362011,"pid":1,"tid":5},
{"ph":"E","ts":5367423,"pid":1,"tid":2},
{"ph":"B","name":"chain1.allSourceFiles","cat":"job","ts":5367457,"pid":1,"tid":2},
{"ph":"E","ts":5368820,"pid":1,"tid":5},
{"ph":"B","name":"chain2.allSourceFiles","cat":"job","ts":5368892,"pid":1,"tid":5},
{"ph":"E","ts":5373102,"pid":1,"tid":2},
{"ph":"B","name":"chain3.allSourceFiles","cat":"job","ts":5373196,"pid":1,"tid":2},
{"ph":"E","ts":5374295,"pid":1,"tid":5},
{"ph":"B","name":"side0.allSourceFiles","cat":"job","ts":5374338,"pid":1,"tid":5},
{"ph":"E","ts":5377549,"pid":1,"tid":2},
{"ph":"B","name":"side1.allSourceFiles","cat":"job","ts":5377590,"pid":1,"tid":2},
{"ph":"E","ts":5383384,"pid":1,"tid":5},
{"ph":"B","name":"side2.allSourceFiles","cat":"job","ts":5383418,"pid":1,"tid":5},
{"ph":"E","ts":5386432,"pid":1,"tid":2},
{"ph":"B","name":"side4.allSourceFiles","cat":"job","ts":5386471,"pid":1,"tid":2},
{"ph":"E","ts":5390567,"pid":1,"tid":5},
{"ph":"B","name":"side3.allSourceFiles","cat":"job","ts":5390639,"pid":1,"tid":5},
{"ph":"E","ts":5394812,"pid":1,"tid":2},
{"ph":"B","name":"side6.allSourceFiles","cat":"job","ts":5394888,"pid":1,"tid":2},
{"ph":"E","ts":5400194,"pid":1,"tid":5},
{"ph":"B","name":"side5.allSourceFiles","cat":"job","ts":5400231,"pid":1,"tid":5},
{"ph":"E","ts":5403523,"pid":1,"tid":2},
{"ph":"B","name":"side7.scalaCompilerBridge","cat":"job","ts":5403602,"pid":1,"tid":2},
{"ph":"E","ts":5407597,"pid":1,"tid":5},
{"ph":"B","name":"side6.scalaCompilerBridge","cat":"job","ts":5407653,"pid":1,"tid":5},
{"ph":"E","ts":5432054,"pid":1,"tid":5},
{"ph":"E","ts":5432075,"pid":1,"tid":2},
{"ph":"E","ts":5432087,"pid":1,"tid":4},
{"ph":"B","name":"side4.scalaCompilerBridge","cat":"job","ts":5432125,"pid":1,"tid":2},
{"ph":"B","name":"side3.scalaCompilerBridge","cat":"job","ts":5432165,"pid":1,"tid":5},
{"ph":"B","name":"side5.scalaCompilerBridge","cat":"job","ts":5432185,"pid":1,"tid":4},
{"ph":"E","ts":5439742,"pid":1,"tid":5},
{"ph":"E","ts":5439790,"pid":1,"tid":2},
{"ph":"E","ts":5439835,"pid":1,"tid":4},
{"ph":"B","name":"side1.scalaCompilerBridge","cat":"job","ts":5439840,"pid":1,"tid":5},
{"ph":"B","name":"side2.scalaCompilerBridge","cat":"job","ts":5439889,"pid":1,"tid":2},
{"ph":"B","name":"side0.scalaCompilerBridge","cat":"job","ts":5439927,"pid":1,"tid":4},
{"ph":"E","ts":5448691,"pid":1,"tid":5},
{"ph":"E","ts":5448712,"pid":1,"tid":4},
{"ph":"E","ts":5448722,"pid":1,"tid":2},
{"ph":"B","name":"common.scalacPluginClasspath","cat":"job","ts":5448762,"pid":1,"tid":2},
{"ph":"B","name":"common.scalaCompilerClasspath","cat":"job","ts":5448806,"pid":1,"tid":4},
{"ph":"B","name":"common.enablePluginScalacOptions","cat":"job","ts":5448828,"pid":1,"tid":5},
{"ph":"E","ts":5451421,"pid":1,"tid":2},
{"ph":"E","ts":5451454,"pid":1,"tid":5},
{"ph":"B","name":"chain0.scalaCompilerBridge","cat":"job","ts":5451517,"pid":1,"tid":5},
{"ph":"B","name":"side7.allSourceFiles","cat":"job","ts":5451551,"pid":1,"tid":2},
{"ph":"E","ts":5456839,"pid":1,"tid":5},
{"ph":"B","name":"side7.scalaCompilerClasspath","cat":"job","ts":5457218,"pid":1,"tid":5},
{"ph":"E","ts":5459616,"pid":1,"tid":2},
{"ph":"B","name":"side7.scalacPluginClasspath","cat":"job","ts":5459668,"pid":1,"tid":2},
{"ph":"E","ts":5461956,"pid":1,"tid":2},
{"ph":"B","name":"side7.enablePluginScalacOptions","cat":"job","ts":5461994,"pid":1,"tid":2},
{"ph":"E","ts":5464557,"pid":1,"tid":2},
{"ph":"B","name":"side6.scalacPluginClasspath","cat":"job","ts":5464598,"pid":1,"tid":2},
{"ph":"E","ts":5466311,"pid":1,"tid":2},
{"ph":"B","name":"side6.scalaCompilerClasspath","cat":"job","ts":5466335,"pid":1,"tid":2},
{"ph":"E","ts":5480566,"pid":1,"tid":4},
{"ph":"E","ts":5480599,"pid":1,"tid":5},
{"ph":"B","name":"side6.enablePluginScalacOptions","cat":"job","ts":5480611,"pid":1,"tid":4},
{"ph":"B","name":"side5.scalacPluginClasspath","cat":"job","ts":5480679,"pid":1,"tid":5},
{"ph":"E","ts":5486568,"pid":1,"tid":5},
{"ph":"E","ts":5486605,"pid":1,"tid":4},
{"ph":"B","name":"side5.scalaCompilerClasspath","cat":"job","ts":5486613,"pid":1,"tid":5},
{"ph":"B","name":"side5.enablePluginScalacOptions","cat":"job","ts":5486666,"pid":1,"tid":4},
{"ph":"E","ts":5488952,"pid":1,"tid":4},
{"ph":"B","name":"side4.scalaCompilerClasspath","cat":"job","ts":5488993,"pid":1,"tid":4},
{"ph":"E","ts":5490788,"pid":1,"tid":2},
{"ph":"B","name":"side4.scalacPluginClasspath","cat":"job","ts":5490834,"pid":1,"tid":2},
{"ph":"E","ts":5493658,"pid":1,"tid":2},
{"ph":"B","name":"side4.enablePluginScalacOptions","cat":"job","ts":5493702,"pid":1,"tid":2},
{"ph":"E","ts":5495810,"pid":1,"tid":2},
{"ph":"B","name":"side3.scalaCompilerClasspath","cat":"job","ts":5495843,"pid":1,"tid":2},
{"ph":"E","ts":5517530,"pid":1,"tid":4},
{"ph":"E","ts":5517551,"pid":1,"tid":5},
{"ph":"B","name":"side3.enablePluginScalacOptions","cat":"job","ts":5517585,"pid":1,"tid":4},
{"ph":"B","name":"side3.scalacPluginClasspath","cat":"job","ts":5517619,"pid":1,"tid":5},
{"ph":"E","ts":5519632,"pid":1,"tid":4},
{"ph":"B","name":"side2.scalacPluginClasspath","cat":"job","ts":5519658,"pid":1,"tid":4},
{"ph":"E","ts":5520090,"pid":1,"tid":5},
{"ph":"B","name":"side2.enablePluginScalacOptions","cat":"job","ts":5520112,"pid":1,"tid":5},
{"ph":"E","ts":5523310,"pid":1,"tid":4},
{"ph":"B","name":"side2.scalaCompilerClasspath","cat":"job","ts":5523355,"pid":1,"tid":4},
{"ph":"E","ts":5523457,"pid":1,"tid":5},
{"ph":"B","name":"side1.scalaCompilerClasspath","cat":"job","ts":5523481,"pid":1,"tid":5},
{"ph":"E","ts":5523613,"pid":1,"tid":2},
{"ph":"B","name":"side1.scalacPluginClasspath","cat":"job","ts":5523648,"pid":1,"tid":2},
{"ph":"E","ts":5525640,"pid":1,"tid":2},
{"ph":"B","name":"side1.enablePluginScalacOptions","cat":"job","ts":5525671,"pid":1,"tid":2},
{"ph":"E","ts":5529521,"pid":1,"tid":2},
{"ph":"B","name":"side0.scalacPluginClasspath","cat":"job","ts":5529564,"pid":1,"tid":2},
{"ph":"E","ts":5531681,"pid":1,"tid":2},
{"ph":"B","name":"side0.scalaCompilerClasspath","cat":"job","ts":5531727,"pid":1,"tid":2},
{"ph":"E","ts":5546917,"pid":1,"tid":4},
{"ph":"E","ts":5546940,"pid":1,"tid":5},
{"ph":"B","name":"side0.enablePluginScalacOptions","cat":"job","ts":5546985,"pid":1,"tid":5},
{"ph":"B","name":"chain1.scalaCompilerBridge","cat":"job","ts":5547065,"pid":1,"tid":4},
{"ph":"E","ts":5549345,"pid":1,"tid":5},
{"ph":"B","name":"chain0.scalacPluginClasspath","cat":"job","ts":5549379,"pid":1,"tid":5},
{"ph":"E","ts":5551418,"pid":1,"tid":4},
{"ph":"B","name":"chain0.enablePluginScalacOptions","cat":"job","ts":5551448,"pid":1,"tid":4},
{"ph":"E","ts":5551805,"pid":1,"tid":5},
{"ph":"B","name":"chain0.scalaCompilerClasspath","cat":"job","ts":5551823,"pid":1,"tid":5},
{"ph":"E","ts":5551889,"pid":1,"tid":2},
{"ph":"B","name":"common.zincIncrementalCompilation","cat":"job","ts":5551916,"pid":1,"tid":2},
{"ph":"E","ts":5552222,"pid":1,"tid":2},
{"ph":"B","name":"chain0.zincIncrementalCompilation","cat":"job","ts":5552239,"pid":1,"tid":2},
{"ph":"E","ts":5552509,"pid":1,"tid":2},
{"ph":"B","name":"chain1.zincIncrementalCompilation","cat":"job","ts":5552559,"pid":1,"tid":2},
{"ph":"E","ts":5552809,"pid":1,"tid":2},
{"ph":"B","name":"chain2.zincIncrementalCompilation","cat":"job","ts":5552829,"pid":1,"tid":2},
{"ph":"E","ts":5553091,"pid":1,"tid":2},
{"ph":"B","name":"chain3.zincIncrementalCompilation","cat":"job","ts":5553107,"pid":1,"tid":2},
{"ph":"E","ts":5553405,"pid":1,"tid":2},
{"ph":"B","name":"side0.zincIncrementalCompilation","cat":"job","ts":5553425,"pid":1,"tid":2},
{"ph":"E","ts":5553493,"pid":1,"tid":4},
{"ph":"B","name":"side1.zincIncrementalCompilation","cat":"job","ts":5553531,"pid":1,"tid":4},
{"ph":"E","ts":5553699,"pid":1,"tid":2},
{"ph":"B","name":"side2.zincIncrementalCompilation","cat":"job","ts":5553729,"pid":1,"tid":2},
{"ph":"E","ts":5553980,"pid":1,"tid":4},
{"ph":"B","name":"side4.zincIncrementalCompilation","cat":"job","ts":5554005,"pid":1,"tid":4},
{"ph":"E","ts":5554116,"pid":1,"tid":2},
{"ph":"B","name":"side3.zincIncrementalCompilation","cat":"job","ts":5554134,"pid":1,"tid":2},
{"ph":"E","ts":5554366,"pid":1,"tid":4},
{"ph":"B","name":"side6.zincIncrementalCompilation","cat":"job","ts":5554382,"pid":1,"tid":4},
{"ph":"E","ts":5554478,"pid":1,"tid":2},
{"ph":"B","name":"side5.zincIncrementalCompilation","cat":"job","ts":5554526,"pid":1,"tid":2},
{"ph":"E","ts":5554695,"pid":1,"tid":4},
{"ph":"E","ts":5554839,"pid":1,"tid":2},
{"ph":"B","name":"chain2.scalaCompilerBridge","cat":"job","ts":5554918,"pid":1,"tid":2},
{"ph":"B","name":"chain1.scalacPluginClasspath","cat":"job","ts":5554987,"pid":1,"tid":4},
{"ph":"E","ts":5557403,"pid":1,"tid":4},
{"ph":"B","name":"chain1.scalaCompilerClasspath","cat":"job","ts":5557444,"pid":1,"tid":4},
{"ph":"E","ts":5558598,"pid":1,"tid":2},
{"ph":"B","name":"chain1.enablePluginScalacOptions","cat":"job","ts":5558621,"pid":1,"tid":2},
{"ph":"E","ts":5561244,"pid":1,"tid":2},
{"ph":"B","name":"side7.zincIncrementalCompilation","cat":"job","ts":5561569,"pid":1,"tid":2},
{"ph":"E","ts":5562173,"pid":1,"tid":2},
{"ph":"B","name":"chain3.scalaCompilerBridge","cat":"job","ts":5562262,"pid":1,"tid":2},
{"ph":"E","ts":5565801,"pid":1,"tid":2},
{"ph":"B","name":"chain2.scalacPluginClasspath","cat":"job","ts":5565859,"pid":1,"tid":2},
{"ph":"E","ts":5567190,"pid":1,"tid":5},
{"ph":"B","name":"chain2.scalaCompilerClasspath","cat":"job","ts":5567230,"pid":1,"tid":5},
{"ph":"E","ts":5568039,"pid":1,"tid":2},
{"ph":"B","name":"chain2.enablePluginScalacOptions","cat":"job","ts":5568073,"pid":1,"tid":2},
{"ph":"E","ts":5574787,"pid":1,"tid":2},
{"ph":"B","name":"common.allScalacOptions","cat":"job","ts":5574966,"pid":1,"tid":2},
{"ph":"E","ts":5576136,"pid":1,"tid":2},
{"ph":"B","name":"chain3.scalacPluginClasspath","cat":"job","ts":5576182,"pid":1,"tid":2},
{"ph":"E","ts":5577523,"pid":1,"tid":4},
{"ph":"B","name":"chain3.enablePluginScalacOptions","cat":"job","ts":5577668,"pid":1,"tid":4},
{"ph":"E","ts":5579096,"pid":1,"tid":2},
{"ph":"B","name":"chain3.scalaCompilerClasspath","cat":"job","ts":5579138,"pid":1,"tid":2},
{"ph":"E","ts":5580638,"pid":1,"tid":4},
{"ph":"B","name":"side7.transitiveCoursierProjects","cat":"job","ts":5580776,"pid":1,"tid":4},
{"ph":"E","ts":5601917,"pid":1,"tid":5},
{"ph":"B","name":"side6.transitiveCoursierProjects","cat":"job","ts":5601994,"pid":1,"tid":5},
{"ph":"E","ts":5609945,"pid":1,"tid":2},
{"ph":"B","name":"side5.transitiveCoursierProjects","cat":"job","ts":5609987,"pid":1,"tid":2},
{"ph":"E","ts":5617948,"pid":1,"tid":5},
{"ph":"E","ts":5617970,"pid":1,"tid":2},
{"ph":"E","ts":5617987,"pid":1,"tid":4},
{"ph":"B","name":"side4.transitiveCoursierProjects","cat":"job","ts":5618011,"pid":1,"tid":5},
{"ph":"B","name":"side2.transitiveCoursierProjects","cat":"job","ts":5618071,"pid":1,"tid":4},
{"ph":"B","name":"side3.transitiveCoursierProjects","cat":"job","ts":5618099,"pid":1,"tid":2},
{"ph":"E","ts":5619752,"pid":1,"tid":2},
{"ph":"E","ts":5619766,"pid":1,"tid":4},
{"ph":"E","ts":5619798,"pid":1,"tid":5},
{"ph":"B","name":"side0.transitiveCoursierProjects","cat":"job","ts":5619813,"pid":1,"tid":4},
{"ph":"B","name":"side1.transitiveCoursierProjects","cat":"job","ts":5619875,"pid":1,"tid":2},
{"ph":"B","name":"chain0.transitiveCoursierProjects","cat":"job","ts":5619920,"pid":1,"tid":5},
{"ph":"E","ts":5621257,"pid":1,"tid":2},
{"ph":"E","ts":5621275,"pid":1,"tid":5},
{"ph":"E","ts":5621304,"pid":1,"tid":4},
{"ph":"B","name":"side7.allScalacOptions","cat":"job","ts":5621328,"pid":1,"tid":5},
{"ph":"B","name":"side5.allScalacOptions","cat":"job","ts":5621354,"pid":1,"tid":4},
{"ph":"B","name":"side6.allScalacOptions","cat":"job","ts":5621380,"pid":1,"tid":2},
{"ph":"E","ts":5621731,"pid":1,"tid":4},
{"ph":"B","name":"side4.allScalacOptions","cat":"job","ts":5621752,"pid":1,"tid":4},
{"ph":"E","ts":5621802,"pid":1,"tid":2},
{"ph":"B","name":"side3.allScalacOptions","cat":"job","ts":5621820,"pid":1,"tid":2},
{"ph":"E","ts":5621880,"pid":1,"tid":5},
{"ph":"B","name":"side2.allScalacOptions","cat":"job","ts":5621902,"pid":1,"tid":5},
{"ph":"E","ts":5622054,"pid":1,"tid":4},
{"ph":"B","name":"side1.allScalacOptions","cat":"job","ts":5622071,"pid":1,"tid":4},
{"ph":"E","ts":5622101,"pid":1,"tid":2},
{"ph":"B","name":"side0.allScalacOptions","cat":"job","ts":5622154,"pid":1,"tid":2},
{"ph":"E","ts":5622200,"pid":1,"tid":5},
{"ph":"B","name":"chain0.allScalacOptions","cat":"job","ts":5622249,"pid":1,"tid":5},
{"ph":"E","ts":5622337,"pid":1,"tid":4},
{"ph":"E","ts":5622413,"pid":1,"tid":2},
{"ph":"B","name":"chain1.allScalacOptions","cat":"job","ts":5622432,"pid":1,"tid":2},
{"ph":"B","name":"chain2.allScalacOptions","cat":"job","ts":5622475,"pid":1,"tid":4},
{"ph":"E","ts":5622547,"pid":1,"tid":5},
{"ph":"B","name":"common.resolvedMvnDeps.super.javalib.JavaModule","cat":"job","ts":5622612,"pid":1,"tid":5},
{"ph":"E","ts":5622806,"pid":1,"tid":4},
{"ph":"B","name":"chain3.allScalacOptions","cat":"job","ts":5622838,"pid":1,"tid":4},
{"ph":"E","ts":5622873,"pid":1,"tid":2},
{"ph":"B","name":"chain1.transitiveCoursierProjects","cat":"job","ts":5622974,"pid":1,"tid":2},
{"ph":"E","ts":5623129,"pid":1,"tid":4},
{"ph":"B","name":"side6.resolvedMvnDeps.super.javalib.JavaModule","cat":"job","ts":5623284,"pid":1,"tid":4},
{"ph":"E","ts":5624257,"pid":1,"tid":2},
{"ph":"B","name":"side7.resolvedMvnDeps.super.javalib.JavaModule","cat":"job","ts":5624299,"pid":1,"tid":2},
{"ph":"E","ts":5631775,"pid":1,"tid":5},
{"ph":"E","ts":5631792,"pid":1,"tid":4},
{"ph":"E","ts":5631803,"pid":1,"tid":2},
{"ph":"B","name":"side5.resolvedMvnDeps.super.javalib.JavaModule","cat":"job","ts":5631811,"pid":1,"tid":5},
{"ph":"B","name":"side4.resolvedMvnDeps.super.javalib.JavaModule","cat":"job","ts":5631845,"pid":1,"tid":4},
{"ph":"B","name":"side3.resolvedMvnDeps.super.javalib.JavaModule","cat":"job","ts":5631873,"pid":1,"tid":2},
{"ph":"E","ts":5639097,"pid":1,"tid":2},
{"ph":"E","ts":5639109,"pid":1,"tid":4},
{"ph":"E","ts":5639138,"pid":1,"tid":5},
{"ph":"B","name":"side0.resolvedMvnDeps.super.javalib.JavaModule","cat":"job","ts":5639162,"pid":1,"tid":5},
{"ph":"B","name":"side1.resolvedMvnDeps.super.javalib.JavaModule","cat":"job","ts":5639228,"pid":1,"tid":4},
{"ph":"B","name":"side2.resolvedMvnDeps.super.javalib.JavaModule","cat":"job","ts":5639259,"pid":1,"tid":2},
{"ph":"E","ts":5652147,"pid":1,"tid":4},
{"ph":"E","ts":5652178,"pid":1,"tid":5},
{"ph":"E","ts":5652191,"pid":1,"tid":2},
{"ph":"B","name":"chain0.resolvedMvnDeps.super.javalib.JavaModule","cat":"job","ts":5652197,"pid":1,"tid":4},
{"ph":"B","name":"chain2.transitiveCoursierProjects","cat":"job","ts":5652264,"pid":1,"tid":2},
{"ph":"B","name":"common.resolvedMvnDeps","cat":"job","ts":5652309,"pid":1,"tid":5},
{"ph":"E","ts":5652790,"pid":1,"tid":5},
{"ph":"B","name":"side6.resolvedMvnDeps","cat":"job","ts":5652822,"pid":1,"tid":5},
{"ph":"E","ts":5653132,"pid":1,"tid":5},
{"ph":"B","name":"side7.resolvedMvnDeps","cat":"job","ts":5653151,"pid":1,"tid":5},
{"ph":"E","ts":5653419,"pid":1,"tid":5},
{"ph":"B","name":"side3.resolvedMvnDeps","cat":"job","ts":5653434,"pid":1,"tid":5},
{"ph":"E","ts":5653692,"pid":1,"tid":5},
{"ph":"B","name":"side4.resolvedMvnDeps","cat":"job","ts":5653705,"pid":1,"tid":5},
{"ph":"E","ts":5653743,"pid":1,"tid":6},
{"ph":"B","name":"side5.resolvedMvnDeps","cat":"job","ts":5653771,"pid":1,"tid":6},
{"ph":"E","ts":5653904,"pid":1,"tid":2},
{"ph":"E","ts":5653945,"pid":1,"tid":5},
{"ph":"B","name":"side1.resolvedMvnDeps","cat":"job","ts":5653953,"pid":1,"tid":2},
{"ph":"B","name":"side0.resolvedMvnDeps","cat":"job","ts":5653966,"pid":1,"tid":5},
{"ph":"E","ts":5654084,"pid":1,"tid":6},
{"ph":"B","name":"side2.resolvedMvnDeps","cat":"job","ts":5654102,"pid":1,"tid":6},
{"ph":"E","ts":5654200,"pid":1,"tid":5},
{"ph":"B","name":"chain1.resolvedMvnDeps.super.javalib.JavaModule","cat":"job","ts":5654230,"pid":1,"tid":5},
{"ph":"E","ts":5654378,"pid":1,"tid":2},
{"ph":"E","ts":5654412,"pid":1,"tid":6},
{"ph":"B","name":"common.compileClasspath","cat":"job","ts":5654457,"pid":1,"tid":2},
{"ph":"B","name":"mill.javalib.JvmWorkerModule/internalWorkerClassLoader","cat":"job","ts":5654484,"pid":1,"tid":6},
{"ph":"E","ts":5654831,"pid":1,"tid":2},
{"ph":"B","name":"chain3.transitiveCoursierProjects","cat":"job","ts":5654853,"pid":1,"tid":2},
{"ph":"E","ts":5656447,"pid":1,"tid":6},
{"ph":"B","name":"chain2.resolvedMvnDeps.super.javalib.JavaModule","cat":"job","ts":5656516,"pid":1,"tid":6},
{"ph":"E","ts":5656547,"pid":1,"tid":2},
{"ph":"B","name":"mill.javalib.JvmWorkerModule/internalWorker","cat":"job","ts":5656607,"pid":1,"tid":2},
{"ph":"E","ts":5658286,"pid":1,"tid":4},
{"ph":"B","name":"chain3.resolvedMvnDeps.super.javalib.JavaModule","cat":"job","ts":5658328,"pid":1,"tid":4},
{"ph":"E","ts":5659376,"pid":1,"tid":5},
{"ph":"B","name":"chain0.resolvedMvnDeps","cat":"job","ts":5659414,"pid":1,"tid":5},
{"ph":"E","ts":5659809,"pid":1,"tid":5},
{"ph":"B","name":"chain1.resolvedMvnDeps","cat":"job","ts":5659837,"pid":1,"tid":5},
{"ph":"E","ts":5660539,"pid":1,"tid":5},
{"ph":"E","ts":5664469,"pid":1,"tid":6},
{"ph":"B","name":"chain2.resolvedMvnDeps","cat":"job","ts":5664641,"pid":1,"tid":6},
{"ph":"E","ts":5665199,"pid":1,"tid":6},
{"ph":"E","ts":5665521,"pid":1,"tid":4},
{"ph":"B","name":"chain3.resolvedMvnDeps","cat":"job","ts":5665563,"pid":1,"tid":4},
{"ph":"E","ts":5665922,"pid":1,"tid":4},
{"ph":"E","ts":5669581,"pid":1,"tid":2},
{"ph":"B","name":"common.compile","cat":"job","ts":5669717,"pid":1,"tid":6},
{"ph":"C","name":"CPU Count","ts":6022960,"pid":1,"args":{"CPUS":14}},
{"ph":"C","name":"CPU Load 0.0-1.0","ts":6022960,"pid":1,"args":{"load":0.4486719310839914}},
{"ph":"C","name":"CPU Count","ts":7026200,"pid":1,"args":{"CPUS":14}},
{"ph":"C","name":"CPU Load 0.0-1.0","ts":7026200,"pid":1,"args":{"load":0.26815240833932424}},
{"ph":"C","name":"CPU Count","ts":8029372,"pid":1,"args":{"CPUS":14}},
{"ph":"C","name":"CPU Load 0.0-1.0","ts":8029372,"pid":1,"args":{"load":0.4939329050678087}},
{"ph":"E","ts":8447413,"pid":1,"tid":6},
{"ph":"B","name":"side6.upstreamCompileOutput","cat":"job","ts":8447591,"pid":1,"tid":6},
{"ph":"B","name":"side5.upstreamCompileOutput","cat":"job","ts":8447634,"pid":1,"tid":2},
{"ph":"B","name":"side3.upstreamCompileOutput","cat":"job","ts":8447653,"pid":1,"tid":4},
{"ph":"B","name":"side7.upstreamCompileOutput","cat":"job","ts":8447674,"pid":1,"tid":5},
{"ph":"E","ts":8448487,"pid":1,"tid":6},
{"ph":"E","ts":8448506,"pid":1,"tid":2},
{"ph":"B","name":"side4.upstreamCompileOutput","cat":"job","ts":8448508,"pid":1,"tid":6},
{"ph":"E","ts":8448533,"pid":1,"tid":5},
{"ph":"E","ts":8448545,"pid":1,"tid":4},
{"ph":"B","name":"side2.upstreamCompileOutput","cat":"job","ts":8448553,"pid":1,"tid":2},
{"ph":"B","name":"side0.upstreamCompileOutput","cat":"job","ts":8448586,"pid":1,"tid":4},
{"ph":"B","name":"side1.upstreamCompileOutput","cat":"job","ts":8448607,"pid":1,"tid":5},
{"ph":"E","ts":8448856,"pid":1,"tid":6},
{"ph":"B","name":"chain0.upstreamCompileOutput","cat":"job","ts":8448876,"pid":1,"tid":6},
{"ph":"E","ts":8448967,"pid":1,"tid":4},
{"ph":"E","ts":8448979,"pid":1,"tid":5},
{"ph":"E","ts":8449019,"pid":1,"tid":2},
{"ph":"B","name":"chain0.compileClasspath","cat":"job","ts":8449053,"pid":1,"tid":2},
{"ph":"B","name":"side7.compileClasspath","cat":"job","ts":8449103,"pid":1,"tid":5},
{"ph":"B","name":"side6.compileClasspath","cat":"job","ts":8449129,"pid":1,"tid":4},
{"ph":"E","ts":8449254,"pid":1,"tid":6},
{"ph":"B","name":"side5.compileClasspath","cat":"job","ts":8449279,"pid":1,"tid":6},
{"ph":"E","ts":8449522,"pid":1,"tid":5},
{"ph":"B","name":"side4.compileClasspath","cat":"job","ts":8449536,"pid":1,"tid":5},
{"ph":"E","ts":8449669,"pid":1,"tid":6},
{"ph":"E","ts":8449691,"pid":1,"tid":4},
{"ph":"B","name":"side3.compileClasspath","cat":"job","ts":8449695,"pid":1,"tid":6},
{"ph":"E","ts":8449717,"pid":1,"tid":2},
{"ph":"B","name":"side2.compileClasspath","cat":"job","ts":8449726,"pid":1,"tid":4},
{"ph":"B","name":"side1.compileClasspath","cat":"job","ts":8449751,"pid":1,"tid":2},
{"ph":"E","ts":8449838,"pid":1,"tid":5},
{"ph":"B","name":"side0.compileClasspath","cat":"job","ts":8449851,"pid":1,"tid":5},
{"ph":"E","ts":8450228,"pid":1,"tid":4},
{"ph":"E","ts":8450236,"pid":1,"tid":5},
{"ph":"E","ts":8450250,"pid":1,"tid":2},
{"ph":"E","ts":8450257,"pid":1,"tid":6},
{"ph":"B","name":"side5.compile","cat":"job","ts":8450507,"pid":1,"tid":2},
{"ph":"B","name":"side7.compile","cat":"job","ts":8450526,"pid":1,"tid":4},
{"ph":"B","name":"side6.compile","cat":"job","ts":8450542,"pid":1,"tid":5},
{"ph":"B","name":"side1.compile","cat":"job","ts":8450558,"pid":1,"tid":6},
{"ph":"C","name":"CPU Count","ts":9033744,"pid":1,"args":{"CPUS":14}},
{"ph":"C","name":"CPU Load 0.0-1.0","ts":9033744,"pid":1,"args":{"load":0.5661186561829878}},
{"ph":"C","name":"CPU Count","ts":10036022,"pid":1,"args":{"CPUS":14}},
{"ph":"C","name":"CPU Load 0.0-1.0","ts":10036022,"pid":1,"args":{"load":0.6640344580043073}},
{"ph":"C","name":"CPU Count","ts":11039519,"pid":1,"args":{"CPUS":14}},
{"ph":"C","name":"CPU Load 0.0-1.0","ts":11039519,"pid":1,"args":{"load":0.6499642090193272}},
{"ph":"E","ts":11297509,"pid":1,"tid":6},
{"ph":"B","name":"side2.compile","cat":"job","ts":11297577,"pid":1,"tid":6},
{"ph":"E","ts":11304512,"pid":1,"tid":5},
{"ph":"B","name":"side4.compile","cat":"job","ts":11304558,"pid":1,"tid":5},
{"ph":"E","ts":11304835,"pid":1,"tid":2},
{"ph":"E","ts":11304852,"pid":1,"tid":4},
{"ph":"B","name":"side0.compile","cat":"job","ts":11304854,"pid":1,"tid":2},
{"ph":"B","name":"side3.compile","cat":"job","ts":11304901,"pid":1,"tid":4},
{"ph":"C","name":"CPU Count","ts":12040871,"pid":1,"args":{"CPUS":14}},
{"ph":"C","name":"CPU Load 0.0-1.0","ts":12040871,"pid":1,"args":{"load":0.7079136690647482}},
{"ph":"E","ts":12303820,"pid":1,"tid":2},
{"ph":"E","ts":12303857,"pid":1,"tid":4},
{"ph":"B","name":"chain0.compile","cat":"job","ts":12303888,"pid":1,"tid":2},
{"ph":"E","ts":12304388,"pid":1,"tid":6},
{"ph":"E","ts":12304575,"pid":1,"tid":5},
{"ph":"E","ts":12698071,"pid":1,"tid":2},
{"ph":"B","name":"chain1.upstreamCompileOutput","cat":"job","ts":12698182,"pid":1,"tid":6},
{"ph":"B","name":"chain1.compileClasspath","cat":"job","ts":12698238,"pid":1,"tid":2},
{"ph":"E","ts":12698755,"pid":1,"tid":6},
{"ph":"E","ts":12698891,"pid":1,"tid":2},
{"ph":"B","name":"chain1.compile","cat":"job","ts":12698999,"pid":1,"tid":4},
{"ph":"C","name":"CPU Count","ts":13045983,"pid":1,"args":{"CPUS":14}},
{"ph":"C","name":"CPU Load 0.0-1.0","ts":13045983,"pid":1,"args":{"load":0.5035714285714286}},
{"ph":"E","ts":13063264,"pid":1,"tid":4},
{"ph":"B","name":"chain2.upstreamCompileOutput","cat":"job","ts":13063358,"pid":1,"tid":5},
{"ph":"B","name":"chain2.compileClasspath","cat":"job","ts":13063571,"pid":1,"tid":2},
{"ph":"E","ts":13063927,"pid":1,"tid":5},
{"ph":"E","ts":13064275,"pid":1,"tid":2},
{"ph":"B","name":"chain2.compile","cat":"job","ts":13064398,"pid":1,"tid":2},
{"ph":"E","ts":13421290,"pid":1,"tid":2},
{"ph":"B","name":"chain3.upstreamCompileOutput","cat":"job","ts":13421431,"pid":1,"tid":4},
{"ph":"B","name":"chain3.compileClasspath","cat":"job","ts":13421469,"pid":1,"tid":6},
{"ph":"E","ts":13422217,"pid":1,"tid":4},
{"ph":"E","ts":13422361,"pid":1,"tid":6},
{"ph":"B","name":"chain3.compile","cat":"job","ts":13422484,"pid":1,"tid":2},
{"ph":"E","ts":13746158,"pid":1,"tid":2},
{"ph":"B","name":"compileLab","cat":"job","ts":13746269,"pid":1,"tid":2},
{"ph":"E","ts":13747297,"pid":1,"tid":2},
{"ph":"E","ts":13789063,"pid":1,"tid":1},
{"ph":"E","ts":13791275,"pid":1,"tid":1},
{"ph":"E","ts":13795297,"pid":1,"tid":1}
]
